[
{
  "Match": "4",
  "Round": "1",
  "GameDate": "2021-08-22 02:30",
  "Location": "Marcantonio Bentegodi",
  "HomeTeam": "Hellas Verona",
  "AwayTeam": "Sassuolo",
  "Result": "",
  "EventType": "schedule",
  "League": "S-A"
},
{
  "Match": "5",
  "Round": "1",
  "GameDate": "2021-08-22 02:30",
  "Location": "Giuseppe Meazza",
  "HomeTeam": "Inter",
  "AwayTeam": "Genoa",
  "Result": "",
  "EventType": "schedule",
  "League": "S-A"
},
{
  "Match": "3",
  "Round": "1",
  "GameDate": "2021-08-22 04:45",
  "Location": "Carlo Castellani",
  "HomeTeam": "Empoli",
  "AwayTeam": "Lazio",
  "Result": "",
  "EventType": "schedule",
  "League": "S-A"
},
{
  "Match": "9",
  "Round": "1",
  "GameDate": "2021-08-22 04:45",
  "Location": "Olimpico Grande Torino",
  "HomeTeam": "Torino",
  "AwayTeam": "Atalanta",
  "Result": "",
  "EventType": "schedule",
  "League": "S-A"
},
{
  "Match": "1",
  "Round": "1",
  "GameDate": "2021-08-23 02:30",
  "Location": "Renato Dall'Ara",
  "HomeTeam": "Bologna",
  "AwayTeam": "Salernitana",
  "Result": "",
  "EventType": "schedule",
  "League": "S-A"
},
{
  "Match": "10",
  "Round": "1",
  "GameDate": "2021-08-23 02:30",
  "Location": "Stadio Friuli",
  "HomeTeam": "Udinese",
  "AwayTeam": "Juventus",
  "Result": "",
  "EventType": "schedule",
  "League": "S-A"
},
{
  "Match": "6",
  "Round": "1",
  "GameDate": "2021-08-23 04:45",
  "Location": "Diego Armando Maradona",
  "HomeTeam": "Napoli",
  "AwayTeam": "Venezia",
  "Result": "",
  "EventType": "schedule",
  "League": "S-A"
},
{
  "Match": "7",
  "Round": "1",
  "GameDate": "2021-08-23 04:45",
  "Location": "Olimpico",
  "HomeTeam": "Roma",
  "AwayTeam": "Fiorentina",
  "Result": "",
  "EventType": "schedule",
  "League": "S-A"
},
{
  "Match": "2",
  "Round": "1",
  "GameDate": "2021-08-24 02:30",
  "Location": "Sardegna Arena",
  "HomeTeam": "Cagliari",
  "AwayTeam": "Spezia",
  "Result": "",
  "EventType": "schedule",
  "League": "S-A"
},
{
  "Match": "8",
  "Round": "1",
  "GameDate": "2021-08-24 04:45",
  "Location": "Luigi Ferraris",
  "HomeTeam": "Sampdoria",
  "AwayTeam": "Milan",
  "Result": "",
  "EventType": "schedule",
  "League": "S-A"
},
{
  "Match": "20",
  "Round": "2",
  "GameDate": "2021-08-28 02:30",
  "Location": "Stadio Friuli",
  "HomeTeam": "Udinese",
  "AwayTeam": "Venezia",
  "Result": "",
  "EventType": "schedule",
  "League": "S-A"
},
{
  "Match": "14",
  "Round": "2",
  "GameDate": "2021-08-28 04:45",
  "Location": "Marcantonio Bentegodi",
  "HomeTeam": "Hellas Verona",
  "AwayTeam": "Inter",
  "Result": "",
  "EventType": "schedule",
  "League": "S-A"
},
{
  "Match": "11",
  "Round": "2",
  "GameDate": "2021-08-29 02:30",
  "Location": "Gewiss Stadium",
  "HomeTeam": "Atalanta",
  "AwayTeam": "Bologna",
  "Result": "",
  "EventType": "schedule",
  "League": "S-A"
},
{
  "Match": "16",
  "Round": "2",
  "GameDate": "2021-08-29 02:30",
  "Location": "Olimpico",
  "HomeTeam": "Lazio",
  "AwayTeam": "Spezia",
  "Result": "",
  "EventType": "schedule",
  "League": "S-A"
},
{
  "Match": "12",
  "Round": "2",
  "GameDate": "2021-08-29 04:45",
  "Location": "Artemio Franchi",
  "HomeTeam": "Fiorentina",
  "AwayTeam": "Torino",
  "Result": "",
  "EventType": "schedule",
  "League": "S-A"
},
{
  "Match": "15",
  "Round": "2",
  "GameDate": "2021-08-29 04:45",
  "Location": "Allianz Stadium",
  "HomeTeam": "Juventus",
  "AwayTeam": "Empoli",
  "Result": "",
  "EventType": "schedule",
  "League": "S-A"
},
{
  "Match": "13",
  "Round": "2",
  "GameDate": "2021-08-30 02:30",
  "Location": "Luigi Ferraris",
  "HomeTeam": "Genoa",
  "AwayTeam": "Napoli",
  "Result": "",
  "EventType": "schedule",
  "League": "S-A"
},
{
  "Match": "19",
  "Round": "2",
  "GameDate": "2021-08-30 02:30",
  "Location": "Mapei Stadium",
  "HomeTeam": "Sassuolo",
  "AwayTeam": "Sampdoria",
  "Result": "",
  "EventType": "schedule",
  "League": "S-A"
},
{
  "Match": "17",
  "Round": "2",
  "GameDate": "2021-08-30 04:45",
  "Location": "Giuseppe Meazza",
  "HomeTeam": "Milan",
  "AwayTeam": "Cagliari",
  "Result": "",
  "EventType": "schedule",
  "League": "S-A"
},
{
  "Match": "18",
  "Round": "2",
  "GameDate": "2021-08-30 04:45",
  "Location": "Arechi",
  "HomeTeam": "Salernitana",
  "AwayTeam": "Roma",
  "Result": "",
  "EventType": "schedule",
  "League": "S-A"
},
{
  "Match": "21",
  "Round": "3",
  "GameDate": "2021-09-12 23:00",
  "Location": "Gewiss Stadium",
  "HomeTeam": "Atalanta",
  "AwayTeam": "Fiorentina",
  "Result": "",
  "EventType": "schedule",
  "League": "S-A"
},
{
  "Match": "22",
  "Round": "3",
  "GameDate": "2021-09-12 23:00",
  "Location": "Renato Dall'Ara",
  "HomeTeam": "Bologna",
  "AwayTeam": "Hellas Verona",
  "Result": "",
  "EventType": "schedule",
  "League": "S-A"
},
{
  "Match": "23",
  "Round": "3",
  "GameDate": "2021-09-12 23:00",
  "Location": "Sardegna Arena",
  "HomeTeam": "Cagliari",
  "AwayTeam": "Genoa",
  "Result": "",
  "EventType": "schedule",
  "League": "S-A"
},
{
  "Match": "24",
  "Round": "3",
  "GameDate": "2021-09-12 23:00",
  "Location": "Carlo Castellani",
  "HomeTeam": "Empoli",
  "AwayTeam": "Venezia",
  "Result": "",
  "EventType": "schedule",
  "League": "S-A"
},
{
  "Match": "25",
  "Round": "3",
  "GameDate": "2021-09-12 23:00",
  "Location": "Giuseppe Meazza",
  "HomeTeam": "Milan",
  "AwayTeam": "Lazio",
  "Result": "",
  "EventType": "schedule",
  "League": "S-A"
},
{
  "Match": "26",
  "Round": "3",
  "GameDate": "2021-09-12 23:00",
  "Location": "Diego Armando Maradona",
  "HomeTeam": "Napoli",
  "AwayTeam": "Juventus",
  "Result": "",
  "EventType": "schedule",
  "League": "S-A"
},
{
  "Match": "27",
  "Round": "3",
  "GameDate": "2021-09-12 23:00",
  "Location": "Olimpico",
  "HomeTeam": "Roma",
  "AwayTeam": "Sassuolo",
  "Result": "",
  "EventType": "schedule",
  "League": "S-A"
},
{
  "Match": "28",
  "Round": "3",
  "GameDate": "2021-09-12 23:00",
  "Location": "Luigi Ferraris",
  "HomeTeam": "Sampdoria",
  "AwayTeam": "Inter",
  "Result": "",
  "EventType": "schedule",
  "League": "S-A"
},
{
  "Match": "29",
  "Round": "3",
  "GameDate": "2021-09-12 23:00",
  "Location": "Alberto Picco",
  "HomeTeam": "Spezia",
  "AwayTeam": "Udinese",
  "Result": "",
  "EventType": "schedule",
  "League": "S-A"
},
{
  "Match": "30",
  "Round": "3",
  "GameDate": "2021-09-12 23:00",
  "Location": "Olimpico Grande Torino",
  "HomeTeam": "Torino",
  "AwayTeam": "Salernitana",
  "Result": "",
  "EventType": "schedule",
  "League": "S-A"
},
{
  "Match": "31",
  "Round": "4",
  "GameDate": "2021-09-19 23:00",
  "Location": "Carlo Castellani",
  "HomeTeam": "Empoli",
  "AwayTeam": "Sampdoria",
  "Result": "",
  "EventType": "schedule",
  "League": "S-A"
},
{
  "Match": "32",
  "Round": "4",
  "GameDate": "2021-09-19 23:00",
  "Location": "Luigi Ferraris",
  "HomeTeam": "Genoa",
  "AwayTeam": "Fiorentina",
  "Result": "",
  "EventType": "schedule",
  "League": "S-A"
},
{
  "Match": "33",
  "Round": "4",
  "GameDate": "2021-09-19 23:00",
  "Location": "Marcantonio Bentegodi",
  "HomeTeam": "Hellas Verona",
  "AwayTeam": "Roma",
  "Result": "",
  "EventType": "schedule",
  "League": "S-A"
},
{
  "Match": "34",
  "Round": "4",
  "GameDate": "2021-09-19 23:00",
  "Location": "Giuseppe Meazza",
  "HomeTeam": "Inter",
  "AwayTeam": "Bologna",
  "Result": "",
  "EventType": "schedule",
  "League": "S-A"
},
{
  "Match": "35",
  "Round": "4",
  "GameDate": "2021-09-19 23:00",
  "Location": "Allianz Stadium",
  "HomeTeam": "Juventus",
  "AwayTeam": "Milan",
  "Result": "",
  "EventType": "schedule",
  "League": "S-A"
},
{
  "Match": "36",
  "Round": "4",
  "GameDate": "2021-09-19 23:00",
  "Location": "Olimpico",
  "HomeTeam": "Lazio",
  "AwayTeam": "Cagliari",
  "Result": "",
  "EventType": "schedule",
  "League": "S-A"
},
{
  "Match": "37",
  "Round": "4",
  "GameDate": "2021-09-19 23:00",
  "Location": "Arechi",
  "HomeTeam": "Salernitana",
  "AwayTeam": "Atalanta",
  "Result": "",
  "EventType": "schedule",
  "League": "S-A"
},
{
  "Match": "38",
  "Round": "4",
  "GameDate": "2021-09-19 23:00",
  "Location": "Mapei Stadium",
  "HomeTeam": "Sassuolo",
  "AwayTeam": "Torino",
  "Result": "",
  "EventType": "schedule",
  "League": "S-A"
},
{
  "Match": "39",
  "Round": "4",
  "GameDate": "2021-09-19 23:00",
  "Location": "Stadio Friuli",
  "HomeTeam": "Udinese",
  "AwayTeam": "Napoli",
  "Result": "",
  "EventType": "schedule",
  "League": "S-A"
},
{
  "Match": "40",
  "Round": "4",
  "GameDate": "2021-09-19 23:00",
  "Location": "Pier Luigi Penzo",
  "HomeTeam": "Venezia",
  "AwayTeam": "Spezia",
  "Result": "",
  "EventType": "schedule",
  "League": "S-A"
},
{
  "Match": "41",
  "Round": "5",
  "GameDate": "2021-09-22 23:00",
  "Location": "Gewiss Stadium",
  "HomeTeam": "Atalanta",
  "AwayTeam": "Sassuolo",
  "Result": "",
  "EventType": "schedule",
  "League": "S-A"
},
{
  "Match": "42",
  "Round": "5",
  "GameDate": "2021-09-22 23:00",
  "Location": "Renato Dall'Ara",
  "HomeTeam": "Bologna",
  "AwayTeam": "Genoa",
  "Result": "",
  "EventType": "schedule",
  "League": "S-A"
},
{
  "Match": "43",
  "Round": "5",
  "GameDate": "2021-09-22 23:00",
  "Location": "Sardegna Arena",
  "HomeTeam": "Cagliari",
  "AwayTeam": "Empoli",
  "Result": "",
  "EventType": "schedule",
  "League": "S-A"
},
{
  "Match": "44",
  "Round": "5",
  "GameDate": "2021-09-22 23:00",
  "Location": "Artemio Franchi",
  "HomeTeam": "Fiorentina",
  "AwayTeam": "Inter",
  "Result": "",
  "EventType": "schedule",
  "League": "S-A"
},
{
  "Match": "45",
  "Round": "5",
  "GameDate": "2021-09-22 23:00",
  "Location": "Giuseppe Meazza",
  "HomeTeam": "Milan",
  "AwayTeam": "Venezia",
  "Result": "",
  "EventType": "schedule",
  "League": "S-A"
},
{
  "Match": "46",
  "Round": "5",
  "GameDate": "2021-09-22 23:00",
  "Location": "Olimpico",
  "HomeTeam": "Roma",
  "AwayTeam": "Udinese",
  "Result": "",
  "EventType": "schedule",
  "League": "S-A"
},
{
  "Match": "47",
  "Round": "5",
  "GameDate": "2021-09-22 23:00",
  "Location": "Arechi",
  "HomeTeam": "Salernitana",
  "AwayTeam": "Hellas Verona",
  "Result": "",
  "EventType": "schedule",
  "League": "S-A"
},
{
  "Match": "48",
  "Round": "5",
  "GameDate": "2021-09-22 23:00",
  "Location": "Luigi Ferraris",
  "HomeTeam": "Sampdoria",
  "AwayTeam": "Napoli",
  "Result": "",
  "EventType": "schedule",
  "League": "S-A"
},
{
  "Match": "49",
  "Round": "5",
  "GameDate": "2021-09-22 23:00",
  "Location": "Alberto Picco",
  "HomeTeam": "Spezia",
  "AwayTeam": "Juventus",
  "Result": "",
  "EventType": "schedule",
  "League": "S-A"
},
{
  "Match": "50",
  "Round": "5",
  "GameDate": "2021-09-22 23:00",
  "Location": "Olimpico Grande Torino",
  "HomeTeam": "Torino",
  "AwayTeam": "Lazio",
  "Result": "",
  "EventType": "schedule",
  "League": "S-A"
},
{
  "Match": "51",
  "Round": "6",
  "GameDate": "2021-09-26 23:00",
  "Location": "Carlo Castellani",
  "HomeTeam": "Empoli",
  "AwayTeam": "Bologna",
  "Result": "",
  "EventType": "schedule",
  "League": "S-A"
},
{
  "Match": "52",
  "Round": "6",
  "GameDate": "2021-09-26 23:00",
  "Location": "Luigi Ferraris",
  "HomeTeam": "Genoa",
  "AwayTeam": "Hellas Verona",
  "Result": "",
  "EventType": "schedule",
  "League": "S-A"
},
{
  "Match": "53",
  "Round": "6",
  "GameDate": "2021-09-26 23:00",
  "Location": "Giuseppe Meazza",
  "HomeTeam": "Inter",
  "AwayTeam": "Atalanta",
  "Result": "",
  "EventType": "schedule",
  "League": "S-A"
},
{
  "Match": "54",
  "Round": "6",
  "GameDate": "2021-09-26 23:00",
  "Location": "Allianz Stadium",
  "HomeTeam": "Juventus",
  "AwayTeam": "Sampdoria",
  "Result": "",
  "EventType": "schedule",
  "League": "S-A"
},
{
  "Match": "55",
  "Round": "6",
  "GameDate": "2021-09-26 23:00",
  "Location": "Olimpico",
  "HomeTeam": "Lazio",
  "AwayTeam": "Roma",
  "Result": "",
  "EventType": "schedule",
  "League": "S-A"
},
{
  "Match": "56",
  "Round": "6",
  "GameDate": "2021-09-26 23:00",
  "Location": "Diego Armando Maradona",
  "HomeTeam": "Napoli",
  "AwayTeam": "Cagliari",
  "Result": "",
  "EventType": "schedule",
  "League": "S-A"
},
{
  "Match": "57",
  "Round": "6",
  "GameDate": "2021-09-26 23:00",
  "Location": "Mapei Stadium",
  "HomeTeam": "Sassuolo",
  "AwayTeam": "Salernitana",
  "Result": "",
  "EventType": "schedule",
  "League": "S-A"
},
{
  "Match": "58",
  "Round": "6",
  "GameDate": "2021-09-26 23:00",
  "Location": "Alberto Picco",
  "HomeTeam": "Spezia",
  "AwayTeam": "Milan",
  "Result": "",
  "EventType": "schedule",
  "League": "S-A"
},
{
  "Match": "59",
  "Round": "6",
  "GameDate": "2021-09-26 23:00",
  "Location": "Stadio Friuli",
  "HomeTeam": "Udinese",
  "AwayTeam": "Fiorentina",
  "Result": "",
  "EventType": "schedule",
  "League": "S-A"
},
{
  "Match": "60",
  "Round": "6",
  "GameDate": "2021-09-26 23:00",
  "Location": "Pier Luigi Penzo",
  "HomeTeam": "Venezia",
  "AwayTeam": "Torino",
  "Result": "",
  "EventType": "schedule",
  "League": "S-A"
},
{
  "Match": "61",
  "Round": "7",
  "GameDate": "2021-10-04 00:00",
  "Location": "Gewiss Stadium",
  "HomeTeam": "Atalanta",
  "AwayTeam": "Milan",
  "Result": "",
  "EventType": "schedule",
  "League": "S-A"
},
{
  "Match": "62",
  "Round": "7",
  "GameDate": "2021-10-04 00:00",
  "Location": "Renato Dall'Ara",
  "HomeTeam": "Bologna",
  "AwayTeam": "Lazio",
  "Result": "",
  "EventType": "schedule",
  "League": "S-A"
},
{
  "Match": "63",
  "Round": "7",
  "GameDate": "2021-10-04 00:00",
  "Location": "Sardegna Arena",
  "HomeTeam": "Cagliari",
  "AwayTeam": "Venezia",
  "Result": "",
  "EventType": "schedule",
  "League": "S-A"
},
{
  "Match": "64",
  "Round": "7",
  "GameDate": "2021-10-04 00:00",
  "Location": "Artemio Franchi",
  "HomeTeam": "Fiorentina",
  "AwayTeam": "Napoli",
  "Result": "",
  "EventType": "schedule",
  "League": "S-A"
},
{
  "Match": "65",
  "Round": "7",
  "GameDate": "2021-10-04 00:00",
  "Location": "Marcantonio Bentegodi",
  "HomeTeam": "Hellas Verona",
  "AwayTeam": "Spezia",
  "Result": "",
  "EventType": "schedule",
  "League": "S-A"
},
{
  "Match": "66",
  "Round": "7",
  "GameDate": "2021-10-04 00:00",
  "Location": "Olimpico",
  "HomeTeam": "Roma",
  "AwayTeam": "Empoli",
  "Result": "",
  "EventType": "schedule",
  "League": "S-A"
},
{
  "Match": "67",
  "Round": "7",
  "GameDate": "2021-10-04 00:00",
  "Location": "Arechi",
  "HomeTeam": "Salernitana",
  "AwayTeam": "Genoa",
  "Result": "",
  "EventType": "schedule",
  "League": "S-A"
},
{
  "Match": "68",
  "Round": "7",
  "GameDate": "2021-10-04 00:00",
  "Location": "Luigi Ferraris",
  "HomeTeam": "Sampdoria",
  "AwayTeam": "Udinese",
  "Result": "",
  "EventType": "schedule",
  "League": "S-A"
},
{
  "Match": "69",
  "Round": "7",
  "GameDate": "2021-10-04 00:00",
  "Location": "Mapei Stadium",
  "HomeTeam": "Sassuolo",
  "AwayTeam": "Inter",
  "Result": "",
  "EventType": "schedule",
  "League": "S-A"
},
{
  "Match": "70",
  "Round": "7",
  "GameDate": "2021-10-04 00:00",
  "Location": "Olimpico Grande Torino",
  "HomeTeam": "Torino",
  "AwayTeam": "Juventus",
  "Result": "",
  "EventType": "schedule",
  "League": "S-A"
},
{
  "Match": "71",
  "Round": "8",
  "GameDate": "2021-10-18 00:00",
  "Location": "Sardegna Arena",
  "HomeTeam": "Cagliari",
  "AwayTeam": "Sampdoria",
  "Result": "",
  "EventType": "schedule",
  "League": "S-A"
},
{
  "Match": "72",
  "Round": "8",
  "GameDate": "2021-10-18 00:00",
  "Location": "Carlo Castellani",
  "HomeTeam": "Empoli",
  "AwayTeam": "Atalanta",
  "Result": "",
  "EventType": "schedule",
  "League": "S-A"
},
{
  "Match": "73",
  "Round": "8",
  "GameDate": "2021-10-18 00:00",
  "Location": "Luigi Ferraris",
  "HomeTeam": "Genoa",
  "AwayTeam": "Sassuolo",
  "Result": "",
  "EventType": "schedule",
  "League": "S-A"
},
{
  "Match": "74",
  "Round": "8",
  "GameDate": "2021-10-18 00:00",
  "Location": "Allianz Stadium",
  "HomeTeam": "Juventus",
  "AwayTeam": "Roma",
  "Result": "",
  "EventType": "schedule",
  "League": "S-A"
},
{
  "Match": "75",
  "Round": "8",
  "GameDate": "2021-10-18 00:00",
  "Location": "Olimpico",
  "HomeTeam": "Lazio",
  "AwayTeam": "Inter",
  "Result": "",
  "EventType": "schedule",
  "League": "S-A"
},
{
  "Match": "76",
  "Round": "8",
  "GameDate": "2021-10-18 00:00",
  "Location": "Giuseppe Meazza",
  "HomeTeam": "Milan",
  "AwayTeam": "Hellas Verona",
  "Result": "",
  "EventType": "schedule",
  "League": "S-A"
},
{
  "Match": "77",
  "Round": "8",
  "GameDate": "2021-10-18 00:00",
  "Location": "Diego Armando Maradona",
  "HomeTeam": "Napoli",
  "AwayTeam": "Torino",
  "Result": "",
  "EventType": "schedule",
  "League": "S-A"
},
{
  "Match": "78",
  "Round": "8",
  "GameDate": "2021-10-18 00:00",
  "Location": "Alberto Picco",
  "HomeTeam": "Spezia",
  "AwayTeam": "Salernitana",
  "Result": "",
  "EventType": "schedule",
  "League": "S-A"
},
{
  "Match": "79",
  "Round": "8",
  "GameDate": "2021-10-18 00:00",
  "Location": "Stadio Friuli",
  "HomeTeam": "Udinese",
  "AwayTeam": "Bologna",
  "Result": "",
  "EventType": "schedule",
  "League": "S-A"
},
{
  "Match": "80",
  "Round": "8",
  "GameDate": "2021-10-18 00:00",
  "Location": "Pier Luigi Penzo",
  "HomeTeam": "Venezia",
  "AwayTeam": "Fiorentina",
  "Result": "",
  "EventType": "schedule",
  "League": "S-A"
},
{
  "Match": "81",
  "Round": "9",
  "GameDate": "2021-10-25 00:00",
  "Location": "Gewiss Stadium",
  "HomeTeam": "Atalanta",
  "AwayTeam": "Udinese",
  "Result": "",
  "EventType": "schedule",
  "League": "S-A"
},
{
  "Match": "82",
  "Round": "9",
  "GameDate": "2021-10-25 00:00",
  "Location": "Renato Dall'Ara",
  "HomeTeam": "Bologna",
  "AwayTeam": "Milan",
  "Result": "",
  "EventType": "schedule",
  "League": "S-A"
},
{
  "Match": "83",
  "Round": "9",
  "GameDate": "2021-10-25 00:00",
  "Location": "Artemio Franchi",
  "HomeTeam": "Fiorentina",
  "AwayTeam": "Cagliari",
  "Result": "",
  "EventType": "schedule",
  "League": "S-A"
},
{
  "Match": "84",
  "Round": "9",
  "GameDate": "2021-10-25 00:00",
  "Location": "Marcantonio Bentegodi",
  "HomeTeam": "Hellas Verona",
  "AwayTeam": "Lazio",
  "Result": "",
  "EventType": "schedule",
  "League": "S-A"
},
{
  "Match": "85",
  "Round": "9",
  "GameDate": "2021-10-25 00:00",
  "Location": "Giuseppe Meazza",
  "HomeTeam": "Inter",
  "AwayTeam": "Juventus",
  "Result": "",
  "EventType": "schedule",
  "League": "S-A"
},
{
  "Match": "86",
  "Round": "9",
  "GameDate": "2021-10-25 00:00",
  "Location": "Olimpico",
  "HomeTeam": "Roma",
  "AwayTeam": "Napoli",
  "Result": "",
  "EventType": "schedule",
  "League": "S-A"
},
{
  "Match": "87",
  "Round": "9",
  "GameDate": "2021-10-25 00:00",
  "Location": "Arechi",
  "HomeTeam": "Salernitana",
  "AwayTeam": "Empoli",
  "Result": "",
  "EventType": "schedule",
  "League": "S-A"
},
{
  "Match": "88",
  "Round": "9",
  "GameDate": "2021-10-25 00:00",
  "Location": "Luigi Ferraris",
  "HomeTeam": "Sampdoria",
  "AwayTeam": "Spezia",
  "Result": "",
  "EventType": "schedule",
  "League": "S-A"
},
{
  "Match": "89",
  "Round": "9",
  "GameDate": "2021-10-25 00:00",
  "Location": "Mapei Stadium",
  "HomeTeam": "Sassuolo",
  "AwayTeam": "Venezia",
  "Result": "",
  "EventType": "schedule",
  "League": "S-A"
},
{
  "Match": "90",
  "Round": "9",
  "GameDate": "2021-10-25 00:00",
  "Location": "Olimpico Grande Torino",
  "HomeTeam": "Torino",
  "AwayTeam": "Genoa",
  "Result": "",
  "EventType": "schedule",
  "League": "S-A"
},
{
  "Match": "91",
  "Round": "10",
  "GameDate": "2021-10-28 00:00",
  "Location": "Sardegna Arena",
  "HomeTeam": "Cagliari",
  "AwayTeam": "Roma",
  "Result": "",
  "EventType": "schedule",
  "League": "S-A"
},
{
  "Match": "92",
  "Round": "10",
  "GameDate": "2021-10-28 00:00",
  "Location": "Carlo Castellani",
  "HomeTeam": "Empoli",
  "AwayTeam": "Inter",
  "Result": "",
  "EventType": "schedule",
  "League": "S-A"
},
{
  "Match": "93",
  "Round": "10",
  "GameDate": "2021-10-28 00:00",
  "Location": "Allianz Stadium",
  "HomeTeam": "Juventus",
  "AwayTeam": "Sassuolo",
  "Result": "",
  "EventType": "schedule",
  "League": "S-A"
},
{
  "Match": "94",
  "Round": "10",
  "GameDate": "2021-10-28 00:00",
  "Location": "Olimpico",
  "HomeTeam": "Lazio",
  "AwayTeam": "Fiorentina",
  "Result": "",
  "EventType": "schedule",
  "League": "S-A"
},
{
  "Match": "95",
  "Round": "10",
  "GameDate": "2021-10-28 00:00",
  "Location": "Giuseppe Meazza",
  "HomeTeam": "Milan",
  "AwayTeam": "Torino",
  "Result": "",
  "EventType": "schedule",
  "League": "S-A"
},
{
  "Match": "96",
  "Round": "10",
  "GameDate": "2021-10-28 00:00",
  "Location": "Diego Armando Maradona",
  "HomeTeam": "Napoli",
  "AwayTeam": "Bologna",
  "Result": "",
  "EventType": "schedule",
  "League": "S-A"
},
{
  "Match": "97",
  "Round": "10",
  "GameDate": "2021-10-28 00:00",
  "Location": "Luigi Ferraris",
  "HomeTeam": "Sampdoria",
  "AwayTeam": "Atalanta",
  "Result": "",
  "EventType": "schedule",
  "League": "S-A"
},
{
  "Match": "98",
  "Round": "10",
  "GameDate": "2021-10-28 00:00",
  "Location": "Alberto Picco",
  "HomeTeam": "Spezia",
  "AwayTeam": "Genoa",
  "Result": "",
  "EventType": "schedule",
  "League": "S-A"
},
{
  "Match": "99",
  "Round": "10",
  "GameDate": "2021-10-28 00:00",
  "Location": "Stadio Friuli",
  "HomeTeam": "Udinese",
  "AwayTeam": "Hellas Verona",
  "Result": "",
  "EventType": "schedule",
  "League": "S-A"
},
{
  "Match": "100",
  "Round": "10",
  "GameDate": "2021-10-28 00:00",
  "Location": "Pier Luigi Penzo",
  "HomeTeam": "Venezia",
  "AwayTeam": "Salernitana",
  "Result": "",
  "EventType": "schedule",
  "League": "S-A"
},
{
  "Match": "101",
  "Round": "11",
  "GameDate": "2021-11-01 01:00",
  "Location": "Gewiss Stadium",
  "HomeTeam": "Atalanta",
  "AwayTeam": "Lazio",
  "Result": "",
  "EventType": "schedule",
  "League": "S-A"
},
{
  "Match": "102",
  "Round": "11",
  "GameDate": "2021-11-01 01:00",
  "Location": "Renato Dall'Ara",
  "HomeTeam": "Bologna",
  "AwayTeam": "Cagliari",
  "Result": "",
  "EventType": "schedule",
  "League": "S-A"
},
{
  "Match": "103",
  "Round": "11",
  "GameDate": "2021-11-01 01:00",
  "Location": "Artemio Franchi",
  "HomeTeam": "Fiorentina",
  "AwayTeam": "Spezia",
  "Result": "",
  "EventType": "schedule",
  "League": "S-A"
},
{
  "Match": "104",
  "Round": "11",
  "GameDate": "2021-11-01 01:00",
  "Location": "Luigi Ferraris",
  "HomeTeam": "Genoa",
  "AwayTeam": "Venezia",
  "Result": "",
  "EventType": "schedule",
  "League": "S-A"
},
{
  "Match": "105",
  "Round": "11",
  "GameDate": "2021-11-01 01:00",
  "Location": "Marcantonio Bentegodi",
  "HomeTeam": "Hellas Verona",
  "AwayTeam": "Juventus",
  "Result": "",
  "EventType": "schedule",
  "League": "S-A"
},
{
  "Match": "106",
  "Round": "11",
  "GameDate": "2021-11-01 01:00",
  "Location": "Giuseppe Meazza",
  "HomeTeam": "Inter",
  "AwayTeam": "Udinese",
  "Result": "",
  "EventType": "schedule",
  "League": "S-A"
},
{
  "Match": "107",
  "Round": "11",
  "GameDate": "2021-11-01 01:00",
  "Location": "Olimpico",
  "HomeTeam": "Roma",
  "AwayTeam": "Milan",
  "Result": "",
  "EventType": "schedule",
  "League": "S-A"
},
{
  "Match": "108",
  "Round": "11",
  "GameDate": "2021-11-01 01:00",
  "Location": "Arechi",
  "HomeTeam": "Salernitana",
  "AwayTeam": "Napoli",
  "Result": "",
  "EventType": "schedule",
  "League": "S-A"
},
{
  "Match": "109",
  "Round": "11",
  "GameDate": "2021-11-01 01:00",
  "Location": "Mapei Stadium",
  "HomeTeam": "Sassuolo",
  "AwayTeam": "Empoli",
  "Result": "",
  "EventType": "schedule",
  "League": "S-A"
},
{
  "Match": "110",
  "Round": "11",
  "GameDate": "2021-11-01 01:00",
  "Location": "Olimpico Grande Torino",
  "HomeTeam": "Torino",
  "AwayTeam": "Sampdoria",
  "Result": "",
  "EventType": "schedule",
  "League": "S-A"
},
{
  "Match": "111",
  "Round": "12",
  "GameDate": "2021-11-08 01:00",
  "Location": "Sardegna Arena",
  "HomeTeam": "Cagliari",
  "AwayTeam": "Atalanta",
  "Result": "",
  "EventType": "schedule",
  "League": "S-A"
},
{
  "Match": "112",
  "Round": "12",
  "GameDate": "2021-11-08 01:00",
  "Location": "Carlo Castellani",
  "HomeTeam": "Empoli",
  "AwayTeam": "Genoa",
  "Result": "",
  "EventType": "schedule",
  "League": "S-A"
},
{
  "Match": "113",
  "Round": "12",
  "GameDate": "2021-11-08 01:00",
  "Location": "Allianz Stadium",
  "HomeTeam": "Juventus",
  "AwayTeam": "Fiorentina",
  "Result": "",
  "EventType": "schedule",
  "League": "S-A"
},
{
  "Match": "114",
  "Round": "12",
  "GameDate": "2021-11-08 01:00",
  "Location": "Olimpico",
  "HomeTeam": "Lazio",
  "AwayTeam": "Salernitana",
  "Result": "",
  "EventType": "schedule",
  "League": "S-A"
},
{
  "Match": "115",
  "Round": "12",
  "GameDate": "2021-11-08 01:00",
  "Location": "Giuseppe Meazza",
  "HomeTeam": "Milan",
  "AwayTeam": "Inter",
  "Result": "",
  "EventType": "schedule",
  "League": "S-A"
},
{
  "Match": "116",
  "Round": "12",
  "GameDate": "2021-11-08 01:00",
  "Location": "Diego Armando Maradona",
  "HomeTeam": "Napoli",
  "AwayTeam": "Hellas Verona",
  "Result": "",
  "EventType": "schedule",
  "League": "S-A"
},
{
  "Match": "117",
  "Round": "12",
  "GameDate": "2021-11-08 01:00",
  "Location": "Luigi Ferraris",
  "HomeTeam": "Sampdoria",
  "AwayTeam": "Bologna",
  "Result": "",
  "EventType": "schedule",
  "League": "S-A"
},
{
  "Match": "118",
  "Round": "12",
  "GameDate": "2021-11-08 01:00",
  "Location": "Alberto Picco",
  "HomeTeam": "Spezia",
  "AwayTeam": "Torino",
  "Result": "",
  "EventType": "schedule",
  "League": "S-A"
},
{
  "Match": "119",
  "Round": "12",
  "GameDate": "2021-11-08 01:00",
  "Location": "Stadio Friuli",
  "HomeTeam": "Udinese",
  "AwayTeam": "Sassuolo",
  "Result": "",
  "EventType": "schedule",
  "League": "S-A"
},
{
  "Match": "120",
  "Round": "12",
  "GameDate": "2021-11-08 01:00",
  "Location": "Pier Luigi Penzo",
  "HomeTeam": "Venezia",
  "AwayTeam": "Roma",
  "Result": "",
  "EventType": "schedule",
  "League": "S-A"
},
{
  "Match": "121",
  "Round": "13",
  "GameDate": "2021-11-22 01:00",
  "Location": "Gewiss Stadium",
  "HomeTeam": "Atalanta",
  "AwayTeam": "Spezia",
  "Result": "",
  "EventType": "schedule",
  "League": "S-A"
},
{
  "Match": "122",
  "Round": "13",
  "GameDate": "2021-11-22 01:00",
  "Location": "Renato Dall'Ara",
  "HomeTeam": "Bologna",
  "AwayTeam": "Venezia",
  "Result": "",
  "EventType": "schedule",
  "League": "S-A"
},
{
  "Match": "123",
  "Round": "13",
  "GameDate": "2021-11-22 01:00",
  "Location": "Artemio Franchi",
  "HomeTeam": "Fiorentina",
  "AwayTeam": "Milan",
  "Result": "",
  "EventType": "schedule",
  "League": "S-A"
},
{
  "Match": "124",
  "Round": "13",
  "GameDate": "2021-11-22 01:00",
  "Location": "Luigi Ferraris",
  "HomeTeam": "Genoa",
  "AwayTeam": "Roma",
  "Result": "",
  "EventType": "schedule",
  "League": "S-A"
},
{
  "Match": "125",
  "Round": "13",
  "GameDate": "2021-11-22 01:00",
  "Location": "Marcantonio Bentegodi",
  "HomeTeam": "Hellas Verona",
  "AwayTeam": "Empoli",
  "Result": "",
  "EventType": "schedule",
  "League": "S-A"
},
{
  "Match": "126",
  "Round": "13",
  "GameDate": "2021-11-22 01:00",
  "Location": "Giuseppe Meazza",
  "HomeTeam": "Inter",
  "AwayTeam": "Napoli",
  "Result": "",
  "EventType": "schedule",
  "League": "S-A"
},
{
  "Match": "127",
  "Round": "13",
  "GameDate": "2021-11-22 01:00",
  "Location": "Olimpico",
  "HomeTeam": "Lazio",
  "AwayTeam": "Juventus",
  "Result": "",
  "EventType": "schedule",
  "League": "S-A"
},
{
  "Match": "128",
  "Round": "13",
  "GameDate": "2021-11-22 01:00",
  "Location": "Arechi",
  "HomeTeam": "Salernitana",
  "AwayTeam": "Sampdoria",
  "Result": "",
  "EventType": "schedule",
  "League": "S-A"
},
{
  "Match": "129",
  "Round": "13",
  "GameDate": "2021-11-22 01:00",
  "Location": "Mapei Stadium",
  "HomeTeam": "Sassuolo",
  "AwayTeam": "Cagliari",
  "Result": "",
  "EventType": "schedule",
  "League": "S-A"
},
{
  "Match": "130",
  "Round": "13",
  "GameDate": "2021-11-22 01:00",
  "Location": "Olimpico Grande Torino",
  "HomeTeam": "Torino",
  "AwayTeam": "Udinese",
  "Result": "",
  "EventType": "schedule",
  "League": "S-A"
},
{
  "Match": "131",
  "Round": "14",
  "GameDate": "2021-11-29 01:00",
  "Location": "Sardegna Arena",
  "HomeTeam": "Cagliari",
  "AwayTeam": "Salernitana",
  "Result": "",
  "EventType": "schedule",
  "League": "S-A"
},
{
  "Match": "132",
  "Round": "14",
  "GameDate": "2021-11-29 01:00",
  "Location": "Carlo Castellani",
  "HomeTeam": "Empoli",
  "AwayTeam": "Fiorentina",
  "Result": "",
  "EventType": "schedule",
  "League": "S-A"
},
{
  "Match": "133",
  "Round": "14",
  "GameDate": "2021-11-29 01:00",
  "Location": "Allianz Stadium",
  "HomeTeam": "Juventus",
  "AwayTeam": "Atalanta",
  "Result": "",
  "EventType": "schedule",
  "League": "S-A"
},
{
  "Match": "134",
  "Round": "14",
  "GameDate": "2021-11-29 01:00",
  "Location": "Giuseppe Meazza",
  "HomeTeam": "Milan",
  "AwayTeam": "Sassuolo",
  "Result": "",
  "EventType": "schedule",
  "League": "S-A"
},
{
  "Match": "135",
  "Round": "14",
  "GameDate": "2021-11-29 01:00",
  "Location": "Diego Armando Maradona",
  "HomeTeam": "Napoli",
  "AwayTeam": "Lazio",
  "Result": "",
  "EventType": "schedule",
  "League": "S-A"
},
{
  "Match": "136",
  "Round": "14",
  "GameDate": "2021-11-29 01:00",
  "Location": "Olimpico",
  "HomeTeam": "Roma",
  "AwayTeam": "Torino",
  "Result": "",
  "EventType": "schedule",
  "League": "S-A"
},
{
  "Match": "137",
  "Round": "14",
  "GameDate": "2021-11-29 01:00",
  "Location": "Luigi Ferraris",
  "HomeTeam": "Sampdoria",
  "AwayTeam": "Hellas Verona",
  "Result": "",
  "EventType": "schedule",
  "League": "S-A"
},
{
  "Match": "138",
  "Round": "14",
  "GameDate": "2021-11-29 01:00",
  "Location": "Alberto Picco",
  "HomeTeam": "Spezia",
  "AwayTeam": "Bologna",
  "Result": "",
  "EventType": "schedule",
  "League": "S-A"
},
{
  "Match": "139",
  "Round": "14",
  "GameDate": "2021-11-29 01:00",
  "Location": "Stadio Friuli",
  "HomeTeam": "Udinese",
  "AwayTeam": "Genoa",
  "Result": "",
  "EventType": "schedule",
  "League": "S-A"
},
{
  "Match": "140",
  "Round": "14",
  "GameDate": "2021-11-29 01:00",
  "Location": "Pier Luigi Penzo",
  "HomeTeam": "Venezia",
  "AwayTeam": "Inter",
  "Result": "",
  "EventType": "schedule",
  "League": "S-A"
},
{
  "Match": "141",
  "Round": "15",
  "GameDate": "2021-12-02 01:00",
  "Location": "Gewiss Stadium",
  "HomeTeam": "Atalanta",
  "AwayTeam": "Venezia",
  "Result": "",
  "EventType": "schedule",
  "League": "S-A"
},
{
  "Match": "142",
  "Round": "15",
  "GameDate": "2021-12-02 01:00",
  "Location": "Renato Dall'Ara",
  "HomeTeam": "Bologna",
  "AwayTeam": "Roma",
  "Result": "",
  "EventType": "schedule",
  "League": "S-A"
},
{
  "Match": "143",
  "Round": "15",
  "GameDate": "2021-12-02 01:00",
  "Location": "Artemio Franchi",
  "HomeTeam": "Fiorentina",
  "AwayTeam": "Sampdoria",
  "Result": "",
  "EventType": "schedule",
  "League": "S-A"
},
{
  "Match": "144",
  "Round": "15",
  "GameDate": "2021-12-02 01:00",
  "Location": "Luigi Ferraris",
  "HomeTeam": "Genoa",
  "AwayTeam": "Milan",
  "Result": "",
  "EventType": "schedule",
  "League": "S-A"
},
{
  "Match": "145",
  "Round": "15",
  "GameDate": "2021-12-02 01:00",
  "Location": "Marcantonio Bentegodi",
  "HomeTeam": "Hellas Verona",
  "AwayTeam": "Cagliari",
  "Result": "",
  "EventType": "schedule",
  "League": "S-A"
},
{
  "Match": "146",
  "Round": "15",
  "GameDate": "2021-12-02 01:00",
  "Location": "Giuseppe Meazza",
  "HomeTeam": "Inter",
  "AwayTeam": "Spezia",
  "Result": "",
  "EventType": "schedule",
  "League": "S-A"
},
{
  "Match": "147",
  "Round": "15",
  "GameDate": "2021-12-02 01:00",
  "Location": "Olimpico",
  "HomeTeam": "Lazio",
  "AwayTeam": "Udinese",
  "Result": "",
  "EventType": "schedule",
  "League": "S-A"
},
{
  "Match": "148",
  "Round": "15",
  "GameDate": "2021-12-02 01:00",
  "Location": "Arechi",
  "HomeTeam": "Salernitana",
  "AwayTeam": "Juventus",
  "Result": "",
  "EventType": "schedule",
  "League": "S-A"
},
{
  "Match": "149",
  "Round": "15",
  "GameDate": "2021-12-02 01:00",
  "Location": "Mapei Stadium",
  "HomeTeam": "Sassuolo",
  "AwayTeam": "Napoli",
  "Result": "",
  "EventType": "schedule",
  "League": "S-A"
},
{
  "Match": "150",
  "Round": "15",
  "GameDate": "2021-12-02 01:00",
  "Location": "Olimpico Grande Torino",
  "HomeTeam": "Torino",
  "AwayTeam": "Empoli",
  "Result": "",
  "EventType": "schedule",
  "League": "S-A"
},
{
  "Match": "151",
  "Round": "16",
  "GameDate": "2021-12-06 01:00",
  "Location": "Renato Dall'Ara",
  "HomeTeam": "Bologna",
  "AwayTeam": "Fiorentina",
  "Result": "",
  "EventType": "schedule",
  "League": "S-A"
},
{
  "Match": "152",
  "Round": "16",
  "GameDate": "2021-12-06 01:00",
  "Location": "Sardegna Arena",
  "HomeTeam": "Cagliari",
  "AwayTeam": "Torino",
  "Result": "",
  "EventType": "schedule",
  "League": "S-A"
},
{
  "Match": "153",
  "Round": "16",
  "GameDate": "2021-12-06 01:00",
  "Location": "Carlo Castellani",
  "HomeTeam": "Empoli",
  "AwayTeam": "Udinese",
  "Result": "",
  "EventType": "schedule",
  "League": "S-A"
},
{
  "Match": "154",
  "Round": "16",
  "GameDate": "2021-12-06 01:00",
  "Location": "Allianz Stadium",
  "HomeTeam": "Juventus",
  "AwayTeam": "Genoa",
  "Result": "",
  "EventType": "schedule",
  "League": "S-A"
},
{
  "Match": "155",
  "Round": "16",
  "GameDate": "2021-12-06 01:00",
  "Location": "Giuseppe Meazza",
  "HomeTeam": "Milan",
  "AwayTeam": "Salernitana",
  "Result": "",
  "EventType": "schedule",
  "League": "S-A"
},
{
  "Match": "156",
  "Round": "16",
  "GameDate": "2021-12-06 01:00",
  "Location": "Diego Armando Maradona",
  "HomeTeam": "Napoli",
  "AwayTeam": "Atalanta",
  "Result": "",
  "EventType": "schedule",
  "League": "S-A"
},
{
  "Match": "157",
  "Round": "16",
  "GameDate": "2021-12-06 01:00",
  "Location": "Olimpico",
  "HomeTeam": "Roma",
  "AwayTeam": "Inter",
  "Result": "",
  "EventType": "schedule",
  "League": "S-A"
},
{
  "Match": "158",
  "Round": "16",
  "GameDate": "2021-12-06 01:00",
  "Location": "Luigi Ferraris",
  "HomeTeam": "Sampdoria",
  "AwayTeam": "Lazio",
  "Result": "",
  "EventType": "schedule",
  "League": "S-A"
},
{
  "Match": "159",
  "Round": "16",
  "GameDate": "2021-12-06 01:00",
  "Location": "Alberto Picco",
  "HomeTeam": "Spezia",
  "AwayTeam": "Sassuolo",
  "Result": "",
  "EventType": "schedule",
  "League": "S-A"
},
{
  "Match": "160",
  "Round": "16",
  "GameDate": "2021-12-06 01:00",
  "Location": "Pier Luigi Penzo",
  "HomeTeam": "Venezia",
  "AwayTeam": "Hellas Verona",
  "Result": "",
  "EventType": "schedule",
  "League": "S-A"
},
{
  "Match": "161",
  "Round": "17",
  "GameDate": "2021-12-13 01:00",
  "Location": "Artemio Franchi",
  "HomeTeam": "Fiorentina",
  "AwayTeam": "Salernitana",
  "Result": "",
  "EventType": "schedule",
  "League": "S-A"
},
{
  "Match": "162",
  "Round": "17",
  "GameDate": "2021-12-13 01:00",
  "Location": "Luigi Ferraris",
  "HomeTeam": "Genoa",
  "AwayTeam": "Sampdoria",
  "Result": "",
  "EventType": "schedule",
  "League": "S-A"
},
{
  "Match": "163",
  "Round": "17",
  "GameDate": "2021-12-13 01:00",
  "Location": "Marcantonio Bentegodi",
  "HomeTeam": "Hellas Verona",
  "AwayTeam": "Atalanta",
  "Result": "",
  "EventType": "schedule",
  "League": "S-A"
},
{
  "Match": "164",
  "Round": "17",
  "GameDate": "2021-12-13 01:00",
  "Location": "Giuseppe Meazza",
  "HomeTeam": "Inter",
  "AwayTeam": "Cagliari",
  "Result": "",
  "EventType": "schedule",
  "League": "S-A"
},
{
  "Match": "165",
  "Round": "17",
  "GameDate": "2021-12-13 01:00",
  "Location": "Diego Armando Maradona",
  "HomeTeam": "Napoli",
  "AwayTeam": "Empoli",
  "Result": "",
  "EventType": "schedule",
  "League": "S-A"
},
{
  "Match": "166",
  "Round": "17",
  "GameDate": "2021-12-13 01:00",
  "Location": "Olimpico",
  "HomeTeam": "Roma",
  "AwayTeam": "Spezia",
  "Result": "",
  "EventType": "schedule",
  "League": "S-A"
},
{
  "Match": "167",
  "Round": "17",
  "GameDate": "2021-12-13 01:00",
  "Location": "Mapei Stadium",
  "HomeTeam": "Sassuolo",
  "AwayTeam": "Lazio",
  "Result": "",
  "EventType": "schedule",
  "League": "S-A"
},
{
  "Match": "168",
  "Round": "17",
  "GameDate": "2021-12-13 01:00",
  "Location": "Olimpico Grande Torino",
  "HomeTeam": "Torino",
  "AwayTeam": "Bologna",
  "Result": "",
  "EventType": "schedule",
  "League": "S-A"
},
{
  "Match": "169",
  "Round": "17",
  "GameDate": "2021-12-13 01:00",
  "Location": "Stadio Friuli",
  "HomeTeam": "Udinese",
  "AwayTeam": "Milan",
  "Result": "",
  "EventType": "schedule",
  "League": "S-A"
},
{
  "Match": "170",
  "Round": "17",
  "GameDate": "2021-12-13 01:00",
  "Location": "Pier Luigi Penzo",
  "HomeTeam": "Venezia",
  "AwayTeam": "Juventus",
  "Result": "",
  "EventType": "schedule",
  "League": "S-A"
},
{
  "Match": "171",
  "Round": "18",
  "GameDate": "2021-12-20 01:00",
  "Location": "Gewiss Stadium",
  "HomeTeam": "Atalanta",
  "AwayTeam": "Roma",
  "Result": "",
  "EventType": "schedule",
  "League": "S-A"
},
{
  "Match": "172",
  "Round": "18",
  "GameDate": "2021-12-20 01:00",
  "Location": "Renato Dall'Ara",
  "HomeTeam": "Bologna",
  "AwayTeam": "Juventus",
  "Result": "",
  "EventType": "schedule",
  "League": "S-A"
},
{
  "Match": "173",
  "Round": "18",
  "GameDate": "2021-12-20 01:00",
  "Location": "Sardegna Arena",
  "HomeTeam": "Cagliari",
  "AwayTeam": "Udinese",
  "Result": "",
  "EventType": "schedule",
  "League": "S-A"
},
{
  "Match": "174",
  "Round": "18",
  "GameDate": "2021-12-20 01:00",
  "Location": "Artemio Franchi",
  "HomeTeam": "Fiorentina",
  "AwayTeam": "Sassuolo",
  "Result": "",
  "EventType": "schedule",
  "League": "S-A"
},
{
  "Match": "175",
  "Round": "18",
  "GameDate": "2021-12-20 01:00",
  "Location": "Olimpico",
  "HomeTeam": "Lazio",
  "AwayTeam": "Genoa",
  "Result": "",
  "EventType": "schedule",
  "League": "S-A"
},
{
  "Match": "176",
  "Round": "18",
  "GameDate": "2021-12-20 01:00",
  "Location": "Giuseppe Meazza",
  "HomeTeam": "Milan",
  "AwayTeam": "Napoli",
  "Result": "",
  "EventType": "schedule",
  "League": "S-A"
},
{
  "Match": "177",
  "Round": "18",
  "GameDate": "2021-12-20 01:00",
  "Location": "Arechi",
  "HomeTeam": "Salernitana",
  "AwayTeam": "Inter",
  "Result": "",
  "EventType": "schedule",
  "League": "S-A"
},
{
  "Match": "178",
  "Round": "18",
  "GameDate": "2021-12-20 01:00",
  "Location": "Luigi Ferraris",
  "HomeTeam": "Sampdoria",
  "AwayTeam": "Venezia",
  "Result": "",
  "EventType": "schedule",
  "League": "S-A"
},
{
  "Match": "179",
  "Round": "18",
  "GameDate": "2021-12-20 01:00",
  "Location": "Alberto Picco",
  "HomeTeam": "Spezia",
  "AwayTeam": "Empoli",
  "Result": "",
  "EventType": "schedule",
  "League": "S-A"
},
{
  "Match": "180",
  "Round": "18",
  "GameDate": "2021-12-20 01:00",
  "Location": "Olimpico Grande Torino",
  "HomeTeam": "Torino",
  "AwayTeam": "Hellas Verona",
  "Result": "",
  "EventType": "schedule",
  "League": "S-A"
},
{
  "Match": "181",
  "Round": "19",
  "GameDate": "2021-12-23 01:00",
  "Location": "Carlo Castellani",
  "HomeTeam": "Empoli",
  "AwayTeam": "Milan",
  "Result": "",
  "EventType": "schedule",
  "League": "S-A"
},
{
  "Match": "182",
  "Round": "19",
  "GameDate": "2021-12-23 01:00",
  "Location": "Luigi Ferraris",
  "HomeTeam": "Genoa",
  "AwayTeam": "Atalanta",
  "Result": "",
  "EventType": "schedule",
  "League": "S-A"
},
{
  "Match": "183",
  "Round": "19",
  "GameDate": "2021-12-23 01:00",
  "Location": "Marcantonio Bentegodi",
  "HomeTeam": "Hellas Verona",
  "AwayTeam": "Fiorentina",
  "Result": "",
  "EventType": "schedule",
  "League": "S-A"
},
{
  "Match": "184",
  "Round": "19",
  "GameDate": "2021-12-23 01:00",
  "Location": "Giuseppe Meazza",
  "HomeTeam": "Inter",
  "AwayTeam": "Torino",
  "Result": "",
  "EventType": "schedule",
  "League": "S-A"
},
{
  "Match": "185",
  "Round": "19",
  "GameDate": "2021-12-23 01:00",
  "Location": "Allianz Stadium",
  "HomeTeam": "Juventus",
  "AwayTeam": "Cagliari",
  "Result": "",
  "EventType": "schedule",
  "League": "S-A"
},
{
  "Match": "186",
  "Round": "19",
  "GameDate": "2021-12-23 01:00",
  "Location": "Diego Armando Maradona",
  "HomeTeam": "Napoli",
  "AwayTeam": "Spezia",
  "Result": "",
  "EventType": "schedule",
  "League": "S-A"
},
{
  "Match": "187",
  "Round": "19",
  "GameDate": "2021-12-23 01:00",
  "Location": "Olimpico",
  "HomeTeam": "Roma",
  "AwayTeam": "Sampdoria",
  "Result": "",
  "EventType": "schedule",
  "League": "S-A"
},
{
  "Match": "188",
  "Round": "19",
  "GameDate": "2021-12-23 01:00",
  "Location": "Mapei Stadium",
  "HomeTeam": "Sassuolo",
  "AwayTeam": "Bologna",
  "Result": "",
  "EventType": "schedule",
  "League": "S-A"
},
{
  "Match": "189",
  "Round": "19",
  "GameDate": "2021-12-23 01:00",
  "Location": "Stadio Friuli",
  "HomeTeam": "Udinese",
  "AwayTeam": "Salernitana",
  "Result": "",
  "EventType": "schedule",
  "League": "S-A"
},
{
  "Match": "190",
  "Round": "19",
  "GameDate": "2021-12-23 01:00",
  "Location": "Pier Luigi Penzo",
  "HomeTeam": "Venezia",
  "AwayTeam": "Lazio",
  "Result": "",
  "EventType": "schedule",
  "League": "S-A"
},
{
  "Match": "191",
  "Round": "20",
  "GameDate": "2022-01-07 01:00",
  "Location": "Gewiss Stadium",
  "HomeTeam": "Atalanta",
  "AwayTeam": "Torino",
  "Result": "",
  "EventType": "schedule",
  "League": "S-A"
},
{
  "Match": "192",
  "Round": "20",
  "GameDate": "2022-01-07 01:00",
  "Location": "Renato Dall'Ara",
  "HomeTeam": "Bologna",
  "AwayTeam": "Inter",
  "Result": "",
  "EventType": "schedule",
  "League": "S-A"
},
{
  "Match": "193",
  "Round": "20",
  "GameDate": "2022-01-07 01:00",
  "Location": "Artemio Franchi",
  "HomeTeam": "Fiorentina",
  "AwayTeam": "Udinese",
  "Result": "",
  "EventType": "schedule",
  "League": "S-A"
},
{
  "Match": "194",
  "Round": "20",
  "GameDate": "2022-01-07 01:00",
  "Location": "Allianz Stadium",
  "HomeTeam": "Juventus",
  "AwayTeam": "Napoli",
  "Result": "",
  "EventType": "schedule",
  "League": "S-A"
},
{
  "Match": "195",
  "Round": "20",
  "GameDate": "2022-01-07 01:00",
  "Location": "Olimpico",
  "HomeTeam": "Lazio",
  "AwayTeam": "Empoli",
  "Result": "",
  "EventType": "schedule",
  "League": "S-A"
},
{
  "Match": "196",
  "Round": "20",
  "GameDate": "2022-01-07 01:00",
  "Location": "Giuseppe Meazza",
  "HomeTeam": "Milan",
  "AwayTeam": "Roma",
  "Result": "",
  "EventType": "schedule",
  "League": "S-A"
},
{
  "Match": "197",
  "Round": "20",
  "GameDate": "2022-01-07 01:00",
  "Location": "Arechi",
  "HomeTeam": "Salernitana",
  "AwayTeam": "Venezia",
  "Result": "",
  "EventType": "schedule",
  "League": "S-A"
},
{
  "Match": "198",
  "Round": "20",
  "GameDate": "2022-01-07 01:00",
  "Location": "Luigi Ferraris",
  "HomeTeam": "Sampdoria",
  "AwayTeam": "Cagliari",
  "Result": "",
  "EventType": "schedule",
  "League": "S-A"
},
{
  "Match": "199",
  "Round": "20",
  "GameDate": "2022-01-07 01:00",
  "Location": "Mapei Stadium",
  "HomeTeam": "Sassuolo",
  "AwayTeam": "Genoa",
  "Result": "",
  "EventType": "schedule",
  "League": "S-A"
},
{
  "Match": "200",
  "Round": "20",
  "GameDate": "2022-01-07 01:00",
  "Location": "Alberto Picco",
  "HomeTeam": "Spezia",
  "AwayTeam": "Hellas Verona",
  "Result": "",
  "EventType": "schedule",
  "League": "S-A"
},
{
  "Match": "201",
  "Round": "21",
  "GameDate": "2022-01-10 01:00",
  "Location": "Sardegna Arena",
  "HomeTeam": "Cagliari",
  "AwayTeam": "Bologna",
  "Result": "",
  "EventType": "schedule",
  "League": "S-A"
},
{
  "Match": "202",
  "Round": "21",
  "GameDate": "2022-01-10 01:00",
  "Location": "Carlo Castellani",
  "HomeTeam": "Empoli",
  "AwayTeam": "Sassuolo",
  "Result": "",
  "EventType": "schedule",
  "League": "S-A"
},
{
  "Match": "203",
  "Round": "21",
  "GameDate": "2022-01-10 01:00",
  "Location": "Luigi Ferraris",
  "HomeTeam": "Genoa",
  "AwayTeam": "Spezia",
  "Result": "",
  "EventType": "schedule",
  "League": "S-A"
},
{
  "Match": "204",
  "Round": "21",
  "GameDate": "2022-01-10 01:00",
  "Location": "Marcantonio Bentegodi",
  "HomeTeam": "Hellas Verona",
  "AwayTeam": "Salernitana",
  "Result": "",
  "EventType": "schedule",
  "League": "S-A"
},
{
  "Match": "205",
  "Round": "21",
  "GameDate": "2022-01-10 01:00",
  "Location": "Giuseppe Meazza",
  "HomeTeam": "Inter",
  "AwayTeam": "Lazio",
  "Result": "",
  "EventType": "schedule",
  "League": "S-A"
},
{
  "Match": "206",
  "Round": "21",
  "GameDate": "2022-01-10 01:00",
  "Location": "Diego Armando Maradona",
  "HomeTeam": "Napoli",
  "AwayTeam": "Sampdoria",
  "Result": "",
  "EventType": "schedule",
  "League": "S-A"
},
{
  "Match": "207",
  "Round": "21",
  "GameDate": "2022-01-10 01:00",
  "Location": "Olimpico",
  "HomeTeam": "Roma",
  "AwayTeam": "Juventus",
  "Result": "",
  "EventType": "schedule",
  "League": "S-A"
},
{
  "Match": "208",
  "Round": "21",
  "GameDate": "2022-01-10 01:00",
  "Location": "Olimpico Grande Torino",
  "HomeTeam": "Torino",
  "AwayTeam": "Fiorentina",
  "Result": "",
  "EventType": "schedule",
  "League": "S-A"
},
{
  "Match": "209",
  "Round": "21",
  "GameDate": "2022-01-10 01:00",
  "Location": "Stadio Friuli",
  "HomeTeam": "Udinese",
  "AwayTeam": "Atalanta",
  "Result": "",
  "EventType": "schedule",
  "League": "S-A"
},
{
  "Match": "210",
  "Round": "21",
  "GameDate": "2022-01-10 01:00",
  "Location": "Pier Luigi Penzo",
  "HomeTeam": "Venezia",
  "AwayTeam": "Milan",
  "Result": "",
  "EventType": "schedule",
  "League": "S-A"
},
{
  "Match": "211",
  "Round": "22",
  "GameDate": "2022-01-17 01:00",
  "Location": "Gewiss Stadium",
  "HomeTeam": "Atalanta",
  "AwayTeam": "Inter",
  "Result": "",
  "EventType": "schedule",
  "League": "S-A"
},
{
  "Match": "212",
  "Round": "22",
  "GameDate": "2022-01-17 01:00",
  "Location": "Renato Dall'Ara",
  "HomeTeam": "Bologna",
  "AwayTeam": "Napoli",
  "Result": "",
  "EventType": "schedule",
  "League": "S-A"
},
{
  "Match": "213",
  "Round": "22",
  "GameDate": "2022-01-17 01:00",
  "Location": "Artemio Franchi",
  "HomeTeam": "Fiorentina",
  "AwayTeam": "Genoa",
  "Result": "",
  "EventType": "schedule",
  "League": "S-A"
},
{
  "Match": "214",
  "Round": "22",
  "GameDate": "2022-01-17 01:00",
  "Location": "Allianz Stadium",
  "HomeTeam": "Juventus",
  "AwayTeam": "Udinese",
  "Result": "",
  "EventType": "schedule",
  "League": "S-A"
},
{
  "Match": "215",
  "Round": "22",
  "GameDate": "2022-01-17 01:00",
  "Location": "Giuseppe Meazza",
  "HomeTeam": "Milan",
  "AwayTeam": "Spezia",
  "Result": "",
  "EventType": "schedule",
  "League": "S-A"
},
{
  "Match": "216",
  "Round": "22",
  "GameDate": "2022-01-17 01:00",
  "Location": "Olimpico",
  "HomeTeam": "Roma",
  "AwayTeam": "Cagliari",
  "Result": "",
  "EventType": "schedule",
  "League": "S-A"
},
{
  "Match": "217",
  "Round": "22",
  "GameDate": "2022-01-17 01:00",
  "Location": "Arechi",
  "HomeTeam": "Salernitana",
  "AwayTeam": "Lazio",
  "Result": "",
  "EventType": "schedule",
  "League": "S-A"
},
{
  "Match": "218",
  "Round": "22",
  "GameDate": "2022-01-17 01:00",
  "Location": "Luigi Ferraris",
  "HomeTeam": "Sampdoria",
  "AwayTeam": "Torino",
  "Result": "",
  "EventType": "schedule",
  "League": "S-A"
},
{
  "Match": "219",
  "Round": "22",
  "GameDate": "2022-01-17 01:00",
  "Location": "Mapei Stadium",
  "HomeTeam": "Sassuolo",
  "AwayTeam": "Hellas Verona",
  "Result": "",
  "EventType": "schedule",
  "League": "S-A"
},
{
  "Match": "220",
  "Round": "22",
  "GameDate": "2022-01-17 01:00",
  "Location": "Pier Luigi Penzo",
  "HomeTeam": "Venezia",
  "AwayTeam": "Empoli",
  "Result": "",
  "EventType": "schedule",
  "League": "S-A"
},
{
  "Match": "221",
  "Round": "23",
  "GameDate": "2022-01-24 01:00",
  "Location": "Sardegna Arena",
  "HomeTeam": "Cagliari",
  "AwayTeam": "Fiorentina",
  "Result": "",
  "EventType": "schedule",
  "League": "S-A"
},
{
  "Match": "222",
  "Round": "23",
  "GameDate": "2022-01-24 01:00",
  "Location": "Carlo Castellani",
  "HomeTeam": "Empoli",
  "AwayTeam": "Roma",
  "Result": "",
  "EventType": "schedule",
  "League": "S-A"
},
{
  "Match": "223",
  "Round": "23",
  "GameDate": "2022-01-24 01:00",
  "Location": "Luigi Ferraris",
  "HomeTeam": "Genoa",
  "AwayTeam": "Udinese",
  "Result": "",
  "EventType": "schedule",
  "League": "S-A"
},
{
  "Match": "224",
  "Round": "23",
  "GameDate": "2022-01-24 01:00",
  "Location": "Marcantonio Bentegodi",
  "HomeTeam": "Hellas Verona",
  "AwayTeam": "Bologna",
  "Result": "",
  "EventType": "schedule",
  "League": "S-A"
},
{
  "Match": "225",
  "Round": "23",
  "GameDate": "2022-01-24 01:00",
  "Location": "Giuseppe Meazza",
  "HomeTeam": "Inter",
  "AwayTeam": "Venezia",
  "Result": "",
  "EventType": "schedule",
  "League": "S-A"
},
{
  "Match": "226",
  "Round": "23",
  "GameDate": "2022-01-24 01:00",
  "Location": "Olimpico",
  "HomeTeam": "Lazio",
  "AwayTeam": "Atalanta",
  "Result": "",
  "EventType": "schedule",
  "League": "S-A"
},
{
  "Match": "227",
  "Round": "23",
  "GameDate": "2022-01-24 01:00",
  "Location": "Giuseppe Meazza",
  "HomeTeam": "Milan",
  "AwayTeam": "Juventus",
  "Result": "",
  "EventType": "schedule",
  "League": "S-A"
},
{
  "Match": "228",
  "Round": "23",
  "GameDate": "2022-01-24 01:00",
  "Location": "Diego Armando Maradona",
  "HomeTeam": "Napoli",
  "AwayTeam": "Salernitana",
  "Result": "",
  "EventType": "schedule",
  "League": "S-A"
},
{
  "Match": "229",
  "Round": "23",
  "GameDate": "2022-01-24 01:00",
  "Location": "Alberto Picco",
  "HomeTeam": "Spezia",
  "AwayTeam": "Sampdoria",
  "Result": "",
  "EventType": "schedule",
  "League": "S-A"
},
{
  "Match": "230",
  "Round": "23",
  "GameDate": "2022-01-24 01:00",
  "Location": "Olimpico Grande Torino",
  "HomeTeam": "Torino",
  "AwayTeam": "Sassuolo",
  "Result": "",
  "EventType": "schedule",
  "League": "S-A"
},
{
  "Match": "231",
  "Round": "24",
  "GameDate": "2022-02-07 01:00",
  "Location": "Gewiss Stadium",
  "HomeTeam": "Atalanta",
  "AwayTeam": "Cagliari",
  "Result": "",
  "EventType": "schedule",
  "League": "S-A"
},
{
  "Match": "232",
  "Round": "24",
  "GameDate": "2022-02-07 01:00",
  "Location": "Renato Dall'Ara",
  "HomeTeam": "Bologna",
  "AwayTeam": "Empoli",
  "Result": "",
  "EventType": "schedule",
  "League": "S-A"
},
{
  "Match": "233",
  "Round": "24",
  "GameDate": "2022-02-07 01:00",
  "Location": "Artemio Franchi",
  "HomeTeam": "Fiorentina",
  "AwayTeam": "Lazio",
  "Result": "",
  "EventType": "schedule",
  "League": "S-A"
},
{
  "Match": "234",
  "Round": "24",
  "GameDate": "2022-02-07 01:00",
  "Location": "Giuseppe Meazza",
  "HomeTeam": "Inter",
  "AwayTeam": "Milan",
  "Result": "",
  "EventType": "schedule",
  "League": "S-A"
},
{
  "Match": "235",
  "Round": "24",
  "GameDate": "2022-02-07 01:00",
  "Location": "Allianz Stadium",
  "HomeTeam": "Juventus",
  "AwayTeam": "Hellas Verona",
  "Result": "",
  "EventType": "schedule",
  "League": "S-A"
},
{
  "Match": "236",
  "Round": "24",
  "GameDate": "2022-02-07 01:00",
  "Location": "Olimpico",
  "HomeTeam": "Roma",
  "AwayTeam": "Genoa",
  "Result": "",
  "EventType": "schedule",
  "League": "S-A"
},
{
  "Match": "237",
  "Round": "24",
  "GameDate": "2022-02-07 01:00",
  "Location": "Arechi",
  "HomeTeam": "Salernitana",
  "AwayTeam": "Spezia",
  "Result": "",
  "EventType": "schedule",
  "League": "S-A"
},
{
  "Match": "238",
  "Round": "24",
  "GameDate": "2022-02-07 01:00",
  "Location": "Luigi Ferraris",
  "HomeTeam": "Sampdoria",
  "AwayTeam": "Sassuolo",
  "Result": "",
  "EventType": "schedule",
  "League": "S-A"
},
{
  "Match": "239",
  "Round": "24",
  "GameDate": "2022-02-07 01:00",
  "Location": "Stadio Friuli",
  "HomeTeam": "Udinese",
  "AwayTeam": "Torino",
  "Result": "",
  "EventType": "schedule",
  "League": "S-A"
},
{
  "Match": "240",
  "Round": "24",
  "GameDate": "2022-02-07 01:00",
  "Location": "Pier Luigi Penzo",
  "HomeTeam": "Venezia",
  "AwayTeam": "Napoli",
  "Result": "",
  "EventType": "schedule",
  "League": "S-A"
},
{
  "Match": "241",
  "Round": "25",
  "GameDate": "2022-02-14 01:00",
  "Location": "Gewiss Stadium",
  "HomeTeam": "Atalanta",
  "AwayTeam": "Juventus",
  "Result": "",
  "EventType": "schedule",
  "League": "S-A"
},
{
  "Match": "242",
  "Round": "25",
  "GameDate": "2022-02-14 01:00",
  "Location": "Carlo Castellani",
  "HomeTeam": "Empoli",
  "AwayTeam": "Cagliari",
  "Result": "",
  "EventType": "schedule",
  "League": "S-A"
},
{
  "Match": "243",
  "Round": "25",
  "GameDate": "2022-02-14 01:00",
  "Location": "Luigi Ferraris",
  "HomeTeam": "Genoa",
  "AwayTeam": "Salernitana",
  "Result": "",
  "EventType": "schedule",
  "League": "S-A"
},
{
  "Match": "244",
  "Round": "25",
  "GameDate": "2022-02-14 01:00",
  "Location": "Marcantonio Bentegodi",
  "HomeTeam": "Hellas Verona",
  "AwayTeam": "Udinese",
  "Result": "",
  "EventType": "schedule",
  "League": "S-A"
},
{
  "Match": "245",
  "Round": "25",
  "GameDate": "2022-02-14 01:00",
  "Location": "Olimpico",
  "HomeTeam": "Lazio",
  "AwayTeam": "Bologna",
  "Result": "",
  "EventType": "schedule",
  "League": "S-A"
},
{
  "Match": "246",
  "Round": "25",
  "GameDate": "2022-02-14 01:00",
  "Location": "Giuseppe Meazza",
  "HomeTeam": "Milan",
  "AwayTeam": "Sampdoria",
  "Result": "",
  "EventType": "schedule",
  "League": "S-A"
},
{
  "Match": "247",
  "Round": "25",
  "GameDate": "2022-02-14 01:00",
  "Location": "Diego Armando Maradona",
  "HomeTeam": "Napoli",
  "AwayTeam": "Inter",
  "Result": "",
  "EventType": "schedule",
  "League": "S-A"
},
{
  "Match": "248",
  "Round": "25",
  "GameDate": "2022-02-14 01:00",
  "Location": "Mapei Stadium",
  "HomeTeam": "Sassuolo",
  "AwayTeam": "Roma",
  "Result": "",
  "EventType": "schedule",
  "League": "S-A"
},
{
  "Match": "249",
  "Round": "25",
  "GameDate": "2022-02-14 01:00",
  "Location": "Alberto Picco",
  "HomeTeam": "Spezia",
  "AwayTeam": "Fiorentina",
  "Result": "",
  "EventType": "schedule",
  "League": "S-A"
},
{
  "Match": "250",
  "Round": "25",
  "GameDate": "2022-02-14 01:00",
  "Location": "Olimpico Grande Torino",
  "HomeTeam": "Torino",
  "AwayTeam": "Venezia",
  "Result": "",
  "EventType": "schedule",
  "League": "S-A"
},
{
  "Match": "251",
  "Round": "26",
  "GameDate": "2022-02-21 01:00",
  "Location": "Renato Dall'Ara",
  "HomeTeam": "Bologna",
  "AwayTeam": "Spezia",
  "Result": "",
  "EventType": "schedule",
  "League": "S-A"
},
{
  "Match": "252",
  "Round": "26",
  "GameDate": "2022-02-21 01:00",
  "Location": "Sardegna Arena",
  "HomeTeam": "Cagliari",
  "AwayTeam": "Napoli",
  "Result": "",
  "EventType": "schedule",
  "League": "S-A"
},
{
  "Match": "253",
  "Round": "26",
  "GameDate": "2022-02-21 01:00",
  "Location": "Artemio Franchi",
  "HomeTeam": "Fiorentina",
  "AwayTeam": "Atalanta",
  "Result": "",
  "EventType": "schedule",
  "League": "S-A"
},
{
  "Match": "254",
  "Round": "26",
  "GameDate": "2022-02-21 01:00",
  "Location": "Giuseppe Meazza",
  "HomeTeam": "Inter",
  "AwayTeam": "Sassuolo",
  "Result": "",
  "EventType": "schedule",
  "League": "S-A"
},
{
  "Match": "255",
  "Round": "26",
  "GameDate": "2022-02-21 01:00",
  "Location": "Allianz Stadium",
  "HomeTeam": "Juventus",
  "AwayTeam": "Torino",
  "Result": "",
  "EventType": "schedule",
  "League": "S-A"
},
{
  "Match": "256",
  "Round": "26",
  "GameDate": "2022-02-21 01:00",
  "Location": "Olimpico",
  "HomeTeam": "Roma",
  "AwayTeam": "Hellas Verona",
  "Result": "",
  "EventType": "schedule",
  "League": "S-A"
},
{
  "Match": "257",
  "Round": "26",
  "GameDate": "2022-02-21 01:00",
  "Location": "Arechi",
  "HomeTeam": "Salernitana",
  "AwayTeam": "Milan",
  "Result": "",
  "EventType": "schedule",
  "League": "S-A"
},
{
  "Match": "258",
  "Round": "26",
  "GameDate": "2022-02-21 01:00",
  "Location": "Luigi Ferraris",
  "HomeTeam": "Sampdoria",
  "AwayTeam": "Empoli",
  "Result": "",
  "EventType": "schedule",
  "League": "S-A"
},
{
  "Match": "259",
  "Round": "26",
  "GameDate": "2022-02-21 01:00",
  "Location": "Stadio Friuli",
  "HomeTeam": "Udinese",
  "AwayTeam": "Lazio",
  "Result": "",
  "EventType": "schedule",
  "League": "S-A"
},
{
  "Match": "260",
  "Round": "26",
  "GameDate": "2022-02-21 01:00",
  "Location": "Pier Luigi Penzo",
  "HomeTeam": "Venezia",
  "AwayTeam": "Genoa",
  "Result": "",
  "EventType": "schedule",
  "League": "S-A"
},
{
  "Match": "261",
  "Round": "27",
  "GameDate": "2022-02-28 01:00",
  "Location": "Gewiss Stadium",
  "HomeTeam": "Atalanta",
  "AwayTeam": "Sampdoria",
  "Result": "",
  "EventType": "schedule",
  "League": "S-A"
},
{
  "Match": "262",
  "Round": "27",
  "GameDate": "2022-02-28 01:00",
  "Location": "Carlo Castellani",
  "HomeTeam": "Empoli",
  "AwayTeam": "Juventus",
  "Result": "",
  "EventType": "schedule",
  "League": "S-A"
},
{
  "Match": "263",
  "Round": "27",
  "GameDate": "2022-02-28 01:00",
  "Location": "Luigi Ferraris",
  "HomeTeam": "Genoa",
  "AwayTeam": "Inter",
  "Result": "",
  "EventType": "schedule",
  "League": "S-A"
},
{
  "Match": "264",
  "Round": "27",
  "GameDate": "2022-02-28 01:00",
  "Location": "Marcantonio Bentegodi",
  "HomeTeam": "Hellas Verona",
  "AwayTeam": "Venezia",
  "Result": "",
  "EventType": "schedule",
  "League": "S-A"
},
{
  "Match": "265",
  "Round": "27",
  "GameDate": "2022-02-28 01:00",
  "Location": "Olimpico",
  "HomeTeam": "Lazio",
  "AwayTeam": "Napoli",
  "Result": "",
  "EventType": "schedule",
  "League": "S-A"
},
{
  "Match": "266",
  "Round": "27",
  "GameDate": "2022-02-28 01:00",
  "Location": "Giuseppe Meazza",
  "HomeTeam": "Milan",
  "AwayTeam": "Udinese",
  "Result": "",
  "EventType": "schedule",
  "League": "S-A"
},
{
  "Match": "267",
  "Round": "27",
  "GameDate": "2022-02-28 01:00",
  "Location": "Arechi",
  "HomeTeam": "Salernitana",
  "AwayTeam": "Bologna",
  "Result": "",
  "EventType": "schedule",
  "League": "S-A"
},
{
  "Match": "268",
  "Round": "27",
  "GameDate": "2022-02-28 01:00",
  "Location": "Mapei Stadium",
  "HomeTeam": "Sassuolo",
  "AwayTeam": "Fiorentina",
  "Result": "",
  "EventType": "schedule",
  "League": "S-A"
},
{
  "Match": "269",
  "Round": "27",
  "GameDate": "2022-02-28 01:00",
  "Location": "Alberto Picco",
  "HomeTeam": "Spezia",
  "AwayTeam": "Roma",
  "Result": "",
  "EventType": "schedule",
  "League": "S-A"
},
{
  "Match": "270",
  "Round": "27",
  "GameDate": "2022-02-28 01:00",
  "Location": "Olimpico Grande Torino",
  "HomeTeam": "Torino",
  "AwayTeam": "Cagliari",
  "Result": "",
  "EventType": "schedule",
  "League": "S-A"
},
{
  "Match": "271",
  "Round": "28",
  "GameDate": "2022-03-07 01:00",
  "Location": "Renato Dall'Ara",
  "HomeTeam": "Bologna",
  "AwayTeam": "Torino",
  "Result": "",
  "EventType": "schedule",
  "League": "S-A"
},
{
  "Match": "272",
  "Round": "28",
  "GameDate": "2022-03-07 01:00",
  "Location": "Sardegna Arena",
  "HomeTeam": "Cagliari",
  "AwayTeam": "Lazio",
  "Result": "",
  "EventType": "schedule",
  "League": "S-A"
},
{
  "Match": "273",
  "Round": "28",
  "GameDate": "2022-03-07 01:00",
  "Location": "Artemio Franchi",
  "HomeTeam": "Fiorentina",
  "AwayTeam": "Hellas Verona",
  "Result": "",
  "EventType": "schedule",
  "League": "S-A"
},
{
  "Match": "274",
  "Round": "28",
  "GameDate": "2022-03-07 01:00",
  "Location": "Luigi Ferraris",
  "HomeTeam": "Genoa",
  "AwayTeam": "Empoli",
  "Result": "",
  "EventType": "schedule",
  "League": "S-A"
},
{
  "Match": "275",
  "Round": "28",
  "GameDate": "2022-03-07 01:00",
  "Location": "Giuseppe Meazza",
  "HomeTeam": "Inter",
  "AwayTeam": "Salernitana",
  "Result": "",
  "EventType": "schedule",
  "League": "S-A"
},
{
  "Match": "276",
  "Round": "28",
  "GameDate": "2022-03-07 01:00",
  "Location": "Allianz Stadium",
  "HomeTeam": "Juventus",
  "AwayTeam": "Spezia",
  "Result": "",
  "EventType": "schedule",
  "League": "S-A"
},
{
  "Match": "277",
  "Round": "28",
  "GameDate": "2022-03-07 01:00",
  "Location": "Diego Armando Maradona",
  "HomeTeam": "Napoli",
  "AwayTeam": "Milan",
  "Result": "",
  "EventType": "schedule",
  "League": "S-A"
},
{
  "Match": "278",
  "Round": "28",
  "GameDate": "2022-03-07 01:00",
  "Location": "Olimpico",
  "HomeTeam": "Roma",
  "AwayTeam": "Atalanta",
  "Result": "",
  "EventType": "schedule",
  "League": "S-A"
},
{
  "Match": "279",
  "Round": "28",
  "GameDate": "2022-03-07 01:00",
  "Location": "Stadio Friuli",
  "HomeTeam": "Udinese",
  "AwayTeam": "Sampdoria",
  "Result": "",
  "EventType": "schedule",
  "League": "S-A"
},
{
  "Match": "280",
  "Round": "28",
  "GameDate": "2022-03-07 01:00",
  "Location": "Pier Luigi Penzo",
  "HomeTeam": "Venezia",
  "AwayTeam": "Sassuolo",
  "Result": "",
  "EventType": "schedule",
  "League": "S-A"
},
{
  "Match": "281",
  "Round": "29",
  "GameDate": "2022-03-14 01:00",
  "Location": "Gewiss Stadium",
  "HomeTeam": "Atalanta",
  "AwayTeam": "Genoa",
  "Result": "",
  "EventType": "schedule",
  "League": "S-A"
},
{
  "Match": "282",
  "Round": "29",
  "GameDate": "2022-03-14 01:00",
  "Location": "Artemio Franchi",
  "HomeTeam": "Fiorentina",
  "AwayTeam": "Bologna",
  "Result": "",
  "EventType": "schedule",
  "League": "S-A"
},
{
  "Match": "283",
  "Round": "29",
  "GameDate": "2022-03-14 01:00",
  "Location": "Marcantonio Bentegodi",
  "HomeTeam": "Hellas Verona",
  "AwayTeam": "Napoli",
  "Result": "",
  "EventType": "schedule",
  "League": "S-A"
},
{
  "Match": "284",
  "Round": "29",
  "GameDate": "2022-03-14 01:00",
  "Location": "Olimpico",
  "HomeTeam": "Lazio",
  "AwayTeam": "Venezia",
  "Result": "",
  "EventType": "schedule",
  "League": "S-A"
},
{
  "Match": "285",
  "Round": "29",
  "GameDate": "2022-03-14 01:00",
  "Location": "Giuseppe Meazza",
  "HomeTeam": "Milan",
  "AwayTeam": "Empoli",
  "Result": "",
  "EventType": "schedule",
  "League": "S-A"
},
{
  "Match": "286",
  "Round": "29",
  "GameDate": "2022-03-14 01:00",
  "Location": "Arechi",
  "HomeTeam": "Salernitana",
  "AwayTeam": "Sassuolo",
  "Result": "",
  "EventType": "schedule",
  "League": "S-A"
},
{
  "Match": "287",
  "Round": "29",
  "GameDate": "2022-03-14 01:00",
  "Location": "Luigi Ferraris",
  "HomeTeam": "Sampdoria",
  "AwayTeam": "Juventus",
  "Result": "",
  "EventType": "schedule",
  "League": "S-A"
},
{
  "Match": "288",
  "Round": "29",
  "GameDate": "2022-03-14 01:00",
  "Location": "Alberto Picco",
  "HomeTeam": "Spezia",
  "AwayTeam": "Cagliari",
  "Result": "",
  "EventType": "schedule",
  "League": "S-A"
},
{
  "Match": "289",
  "Round": "29",
  "GameDate": "2022-03-14 01:00",
  "Location": "Olimpico Grande Torino",
  "HomeTeam": "Torino",
  "AwayTeam": "Inter",
  "Result": "",
  "EventType": "schedule",
  "League": "S-A"
},
{
  "Match": "290",
  "Round": "29",
  "GameDate": "2022-03-14 01:00",
  "Location": "Stadio Friuli",
  "HomeTeam": "Udinese",
  "AwayTeam": "Roma",
  "Result": "",
  "EventType": "schedule",
  "League": "S-A"
},
{
  "Match": "291",
  "Round": "30",
  "GameDate": "2022-03-21 01:00",
  "Location": "Renato Dall'Ara",
  "HomeTeam": "Bologna",
  "AwayTeam": "Atalanta",
  "Result": "",
  "EventType": "schedule",
  "League": "S-A"
},
{
  "Match": "292",
  "Round": "30",
  "GameDate": "2022-03-21 01:00",
  "Location": "Sardegna Arena",
  "HomeTeam": "Cagliari",
  "AwayTeam": "Milan",
  "Result": "",
  "EventType": "schedule",
  "League": "S-A"
},
{
  "Match": "293",
  "Round": "30",
  "GameDate": "2022-03-21 01:00",
  "Location": "Carlo Castellani",
  "HomeTeam": "Empoli",
  "AwayTeam": "Hellas Verona",
  "Result": "",
  "EventType": "schedule",
  "League": "S-A"
},
{
  "Match": "294",
  "Round": "30",
  "GameDate": "2022-03-21 01:00",
  "Location": "Luigi Ferraris",
  "HomeTeam": "Genoa",
  "AwayTeam": "Torino",
  "Result": "",
  "EventType": "schedule",
  "League": "S-A"
},
{
  "Match": "295",
  "Round": "30",
  "GameDate": "2022-03-21 01:00",
  "Location": "Giuseppe Meazza",
  "HomeTeam": "Inter",
  "AwayTeam": "Fiorentina",
  "Result": "",
  "EventType": "schedule",
  "League": "S-A"
},
{
  "Match": "296",
  "Round": "30",
  "GameDate": "2022-03-21 01:00",
  "Location": "Allianz Stadium",
  "HomeTeam": "Juventus",
  "AwayTeam": "Salernitana",
  "Result": "",
  "EventType": "schedule",
  "League": "S-A"
},
{
  "Match": "297",
  "Round": "30",
  "GameDate": "2022-03-21 01:00",
  "Location": "Diego Armando Maradona",
  "HomeTeam": "Napoli",
  "AwayTeam": "Udinese",
  "Result": "",
  "EventType": "schedule",
  "League": "S-A"
},
{
  "Match": "298",
  "Round": "30",
  "GameDate": "2022-03-21 01:00",
  "Location": "Olimpico",
  "HomeTeam": "Roma",
  "AwayTeam": "Lazio",
  "Result": "",
  "EventType": "schedule",
  "League": "S-A"
},
{
  "Match": "299",
  "Round": "30",
  "GameDate": "2022-03-21 01:00",
  "Location": "Mapei Stadium",
  "HomeTeam": "Sassuolo",
  "AwayTeam": "Spezia",
  "Result": "",
  "EventType": "schedule",
  "League": "S-A"
},
{
  "Match": "300",
  "Round": "30",
  "GameDate": "2022-03-21 01:00",
  "Location": "Pier Luigi Penzo",
  "HomeTeam": "Venezia",
  "AwayTeam": "Sampdoria",
  "Result": "",
  "EventType": "schedule",
  "League": "S-A"
},
{
  "Match": "301",
  "Round": "31",
  "GameDate": "2022-04-03 23:00",
  "Location": "Gewiss Stadium",
  "HomeTeam": "Atalanta",
  "AwayTeam": "Napoli",
  "Result": "",
  "EventType": "schedule",
  "League": "S-A"
},
{
  "Match": "302",
  "Round": "31",
  "GameDate": "2022-04-03 23:00",
  "Location": "Artemio Franchi",
  "HomeTeam": "Fiorentina",
  "AwayTeam": "Empoli",
  "Result": "",
  "EventType": "schedule",
  "League": "S-A"
},
{
  "Match": "303",
  "Round": "31",
  "GameDate": "2022-04-03 23:00",
  "Location": "Marcantonio Bentegodi",
  "HomeTeam": "Hellas Verona",
  "AwayTeam": "Genoa",
  "Result": "",
  "EventType": "schedule",
  "League": "S-A"
},
{
  "Match": "304",
  "Round": "31",
  "GameDate": "2022-04-03 23:00",
  "Location": "Allianz Stadium",
  "HomeTeam": "Juventus",
  "AwayTeam": "Inter",
  "Result": "",
  "EventType": "schedule",
  "League": "S-A"
},
{
  "Match": "305",
  "Round": "31",
  "GameDate": "2022-04-03 23:00",
  "Location": "Olimpico",
  "HomeTeam": "Lazio",
  "AwayTeam": "Sassuolo",
  "Result": "",
  "EventType": "schedule",
  "League": "S-A"
},
{
  "Match": "306",
  "Round": "31",
  "GameDate": "2022-04-03 23:00",
  "Location": "Giuseppe Meazza",
  "HomeTeam": "Milan",
  "AwayTeam": "Bologna",
  "Result": "",
  "EventType": "schedule",
  "League": "S-A"
},
{
  "Match": "307",
  "Round": "31",
  "GameDate": "2022-04-03 23:00",
  "Location": "Arechi",
  "HomeTeam": "Salernitana",
  "AwayTeam": "Torino",
  "Result": "",
  "EventType": "schedule",
  "League": "S-A"
},
{
  "Match": "308",
  "Round": "31",
  "GameDate": "2022-04-03 23:00",
  "Location": "Luigi Ferraris",
  "HomeTeam": "Sampdoria",
  "AwayTeam": "Roma",
  "Result": "",
  "EventType": "schedule",
  "League": "S-A"
},
{
  "Match": "309",
  "Round": "31",
  "GameDate": "2022-04-03 23:00",
  "Location": "Alberto Picco",
  "HomeTeam": "Spezia",
  "AwayTeam": "Venezia",
  "Result": "",
  "EventType": "schedule",
  "League": "S-A"
},
{
  "Match": "310",
  "Round": "31",
  "GameDate": "2022-04-03 23:00",
  "Location": "Stadio Friuli",
  "HomeTeam": "Udinese",
  "AwayTeam": "Cagliari",
  "Result": "",
  "EventType": "schedule",
  "League": "S-A"
},
{
  "Match": "311",
  "Round": "32",
  "GameDate": "2022-04-10 23:00",
  "Location": "Renato Dall'Ara",
  "HomeTeam": "Bologna",
  "AwayTeam": "Sampdoria",
  "Result": "",
  "EventType": "schedule",
  "League": "S-A"
},
{
  "Match": "312",
  "Round": "32",
  "GameDate": "2022-04-10 23:00",
  "Location": "Sardegna Arena",
  "HomeTeam": "Cagliari",
  "AwayTeam": "Juventus",
  "Result": "",
  "EventType": "schedule",
  "League": "S-A"
},
{
  "Match": "313",
  "Round": "32",
  "GameDate": "2022-04-10 23:00",
  "Location": "Carlo Castellani",
  "HomeTeam": "Empoli",
  "AwayTeam": "Spezia",
  "Result": "",
  "EventType": "schedule",
  "League": "S-A"
},
{
  "Match": "314",
  "Round": "32",
  "GameDate": "2022-04-10 23:00",
  "Location": "Luigi Ferraris",
  "HomeTeam": "Genoa",
  "AwayTeam": "Lazio",
  "Result": "",
  "EventType": "schedule",
  "League": "S-A"
},
{
  "Match": "315",
  "Round": "32",
  "GameDate": "2022-04-10 23:00",
  "Location": "Giuseppe Meazza",
  "HomeTeam": "Inter",
  "AwayTeam": "Hellas Verona",
  "Result": "",
  "EventType": "schedule",
  "League": "S-A"
},
{
  "Match": "316",
  "Round": "32",
  "GameDate": "2022-04-10 23:00",
  "Location": "Diego Armando Maradona",
  "HomeTeam": "Napoli",
  "AwayTeam": "Fiorentina",
  "Result": "",
  "EventType": "schedule",
  "League": "S-A"
},
{
  "Match": "317",
  "Round": "32",
  "GameDate": "2022-04-10 23:00",
  "Location": "Olimpico",
  "HomeTeam": "Roma",
  "AwayTeam": "Salernitana",
  "Result": "",
  "EventType": "schedule",
  "League": "S-A"
},
{
  "Match": "318",
  "Round": "32",
  "GameDate": "2022-04-10 23:00",
  "Location": "Mapei Stadium",
  "HomeTeam": "Sassuolo",
  "AwayTeam": "Atalanta",
  "Result": "",
  "EventType": "schedule",
  "League": "S-A"
},
{
  "Match": "319",
  "Round": "32",
  "GameDate": "2022-04-10 23:00",
  "Location": "Olimpico Grande Torino",
  "HomeTeam": "Torino",
  "AwayTeam": "Milan",
  "Result": "",
  "EventType": "schedule",
  "League": "S-A"
},
{
  "Match": "320",
  "Round": "32",
  "GameDate": "2022-04-10 23:00",
  "Location": "Pier Luigi Penzo",
  "HomeTeam": "Venezia",
  "AwayTeam": "Udinese",
  "Result": "",
  "EventType": "schedule",
  "League": "S-A"
},
{
  "Match": "321",
  "Round": "33",
  "GameDate": "2022-04-16 23:00",
  "Location": "Gewiss Stadium",
  "HomeTeam": "Atalanta",
  "AwayTeam": "Hellas Verona",
  "Result": "",
  "EventType": "schedule",
  "League": "S-A"
},
{
  "Match": "322",
  "Round": "33",
  "GameDate": "2022-04-16 23:00",
  "Location": "Sardegna Arena",
  "HomeTeam": "Cagliari",
  "AwayTeam": "Sassuolo",
  "Result": "",
  "EventType": "schedule",
  "League": "S-A"
},
{
  "Match": "323",
  "Round": "33",
  "GameDate": "2022-04-16 23:00",
  "Location": "Artemio Franchi",
  "HomeTeam": "Fiorentina",
  "AwayTeam": "Venezia",
  "Result": "",
  "EventType": "schedule",
  "League": "S-A"
},
{
  "Match": "324",
  "Round": "33",
  "GameDate": "2022-04-16 23:00",
  "Location": "Allianz Stadium",
  "HomeTeam": "Juventus",
  "AwayTeam": "Bologna",
  "Result": "",
  "EventType": "schedule",
  "League": "S-A"
},
{
  "Match": "325",
  "Round": "33",
  "GameDate": "2022-04-16 23:00",
  "Location": "Olimpico",
  "HomeTeam": "Lazio",
  "AwayTeam": "Torino",
  "Result": "",
  "EventType": "schedule",
  "League": "S-A"
},
{
  "Match": "326",
  "Round": "33",
  "GameDate": "2022-04-16 23:00",
  "Location": "Giuseppe Meazza",
  "HomeTeam": "Milan",
  "AwayTeam": "Genoa",
  "Result": "",
  "EventType": "schedule",
  "League": "S-A"
},
{
  "Match": "327",
  "Round": "33",
  "GameDate": "2022-04-16 23:00",
  "Location": "Diego Armando Maradona",
  "HomeTeam": "Napoli",
  "AwayTeam": "Roma",
  "Result": "",
  "EventType": "schedule",
  "League": "S-A"
},
{
  "Match": "328",
  "Round": "33",
  "GameDate": "2022-04-16 23:00",
  "Location": "Luigi Ferraris",
  "HomeTeam": "Sampdoria",
  "AwayTeam": "Salernitana",
  "Result": "",
  "EventType": "schedule",
  "League": "S-A"
},
{
  "Match": "329",
  "Round": "33",
  "GameDate": "2022-04-16 23:00",
  "Location": "Alberto Picco",
  "HomeTeam": "Spezia",
  "AwayTeam": "Inter",
  "Result": "",
  "EventType": "schedule",
  "League": "S-A"
},
{
  "Match": "330",
  "Round": "33",
  "GameDate": "2022-04-16 23:00",
  "Location": "Stadio Friuli",
  "HomeTeam": "Udinese",
  "AwayTeam": "Empoli",
  "Result": "",
  "EventType": "schedule",
  "League": "S-A"
},
{
  "Match": "331",
  "Round": "34",
  "GameDate": "2022-04-24 23:00",
  "Location": "Renato Dall'Ara",
  "HomeTeam": "Bologna",
  "AwayTeam": "Udinese",
  "Result": "",
  "EventType": "schedule",
  "League": "S-A"
},
{
  "Match": "332",
  "Round": "34",
  "GameDate": "2022-04-24 23:00",
  "Location": "Carlo Castellani",
  "HomeTeam": "Empoli",
  "AwayTeam": "Napoli",
  "Result": "",
  "EventType": "schedule",
  "League": "S-A"
},
{
  "Match": "333",
  "Round": "34",
  "GameDate": "2022-04-24 23:00",
  "Location": "Luigi Ferraris",
  "HomeTeam": "Genoa",
  "AwayTeam": "Cagliari",
  "Result": "",
  "EventType": "schedule",
  "League": "S-A"
},
{
  "Match": "334",
  "Round": "34",
  "GameDate": "2022-04-24 23:00",
  "Location": "Marcantonio Bentegodi",
  "HomeTeam": "Hellas Verona",
  "AwayTeam": "Sampdoria",
  "Result": "",
  "EventType": "schedule",
  "League": "S-A"
},
{
  "Match": "335",
  "Round": "34",
  "GameDate": "2022-04-24 23:00",
  "Location": "Giuseppe Meazza",
  "HomeTeam": "Inter",
  "AwayTeam": "Roma",
  "Result": "",
  "EventType": "schedule",
  "League": "S-A"
},
{
  "Match": "336",
  "Round": "34",
  "GameDate": "2022-04-24 23:00",
  "Location": "Olimpico",
  "HomeTeam": "Lazio",
  "AwayTeam": "Milan",
  "Result": "",
  "EventType": "schedule",
  "League": "S-A"
},
{
  "Match": "337",
  "Round": "34",
  "GameDate": "2022-04-24 23:00",
  "Location": "Arechi",
  "HomeTeam": "Salernitana",
  "AwayTeam": "Fiorentina",
  "Result": "",
  "EventType": "schedule",
  "League": "S-A"
},
{
  "Match": "338",
  "Round": "34",
  "GameDate": "2022-04-24 23:00",
  "Location": "Mapei Stadium",
  "HomeTeam": "Sassuolo",
  "AwayTeam": "Juventus",
  "Result": "",
  "EventType": "schedule",
  "League": "S-A"
},
{
  "Match": "339",
  "Round": "34",
  "GameDate": "2022-04-24 23:00",
  "Location": "Olimpico Grande Torino",
  "HomeTeam": "Torino",
  "AwayTeam": "Spezia",
  "Result": "",
  "EventType": "schedule",
  "League": "S-A"
},
{
  "Match": "340",
  "Round": "34",
  "GameDate": "2022-04-24 23:00",
  "Location": "Pier Luigi Penzo",
  "HomeTeam": "Venezia",
  "AwayTeam": "Atalanta",
  "Result": "",
  "EventType": "schedule",
  "League": "S-A"
},
{
  "Match": "341",
  "Round": "35",
  "GameDate": "2022-05-01 23:00",
  "Location": "Gewiss Stadium",
  "HomeTeam": "Atalanta",
  "AwayTeam": "Salernitana",
  "Result": "",
  "EventType": "schedule",
  "League": "S-A"
},
{
  "Match": "342",
  "Round": "35",
  "GameDate": "2022-05-01 23:00",
  "Location": "Sardegna Arena",
  "HomeTeam": "Cagliari",
  "AwayTeam": "Hellas Verona",
  "Result": "",
  "EventType": "schedule",
  "League": "S-A"
},
{
  "Match": "343",
  "Round": "35",
  "GameDate": "2022-05-01 23:00",
  "Location": "Carlo Castellani",
  "HomeTeam": "Empoli",
  "AwayTeam": "Torino",
  "Result": "",
  "EventType": "schedule",
  "League": "S-A"
},
{
  "Match": "344",
  "Round": "35",
  "GameDate": "2022-05-01 23:00",
  "Location": "Allianz Stadium",
  "HomeTeam": "Juventus",
  "AwayTeam": "Venezia",
  "Result": "",
  "EventType": "schedule",
  "League": "S-A"
},
{
  "Match": "345",
  "Round": "35",
  "GameDate": "2022-05-01 23:00",
  "Location": "Giuseppe Meazza",
  "HomeTeam": "Milan",
  "AwayTeam": "Fiorentina",
  "Result": "",
  "EventType": "schedule",
  "League": "S-A"
},
{
  "Match": "346",
  "Round": "35",
  "GameDate": "2022-05-01 23:00",
  "Location": "Diego Armando Maradona",
  "HomeTeam": "Napoli",
  "AwayTeam": "Sassuolo",
  "Result": "",
  "EventType": "schedule",
  "League": "S-A"
},
{
  "Match": "347",
  "Round": "35",
  "GameDate": "2022-05-01 23:00",
  "Location": "Olimpico",
  "HomeTeam": "Roma",
  "AwayTeam": "Bologna",
  "Result": "",
  "EventType": "schedule",
  "League": "S-A"
},
{
  "Match": "348",
  "Round": "35",
  "GameDate": "2022-05-01 23:00",
  "Location": "Luigi Ferraris",
  "HomeTeam": "Sampdoria",
  "AwayTeam": "Genoa",
  "Result": "",
  "EventType": "schedule",
  "League": "S-A"
},
{
  "Match": "349",
  "Round": "35",
  "GameDate": "2022-05-01 23:00",
  "Location": "Alberto Picco",
  "HomeTeam": "Spezia",
  "AwayTeam": "Lazio",
  "Result": "",
  "EventType": "schedule",
  "League": "S-A"
},
{
  "Match": "350",
  "Round": "35",
  "GameDate": "2022-05-01 23:00",
  "Location": "Stadio Friuli",
  "HomeTeam": "Udinese",
  "AwayTeam": "Inter",
  "Result": "",
  "EventType": "schedule",
  "League": "S-A"
},
{
  "Match": "351",
  "Round": "36",
  "GameDate": "2022-05-08 23:00",
  "Location": "Artemio Franchi",
  "HomeTeam": "Fiorentina",
  "AwayTeam": "Roma",
  "Result": "",
  "EventType": "schedule",
  "League": "S-A"
},
{
  "Match": "352",
  "Round": "36",
  "GameDate": "2022-05-08 23:00",
  "Location": "Luigi Ferraris",
  "HomeTeam": "Genoa",
  "AwayTeam": "Juventus",
  "Result": "",
  "EventType": "schedule",
  "League": "S-A"
},
{
  "Match": "353",
  "Round": "36",
  "GameDate": "2022-05-08 23:00",
  "Location": "Marcantonio Bentegodi",
  "HomeTeam": "Hellas Verona",
  "AwayTeam": "Milan",
  "Result": "",
  "EventType": "schedule",
  "League": "S-A"
},
{
  "Match": "354",
  "Round": "36",
  "GameDate": "2022-05-08 23:00",
  "Location": "Giuseppe Meazza",
  "HomeTeam": "Inter",
  "AwayTeam": "Empoli",
  "Result": "",
  "EventType": "schedule",
  "League": "S-A"
},
{
  "Match": "355",
  "Round": "36",
  "GameDate": "2022-05-08 23:00",
  "Location": "Olimpico",
  "HomeTeam": "Lazio",
  "AwayTeam": "Sampdoria",
  "Result": "",
  "EventType": "schedule",
  "League": "S-A"
},
{
  "Match": "356",
  "Round": "36",
  "GameDate": "2022-05-08 23:00",
  "Location": "Arechi",
  "HomeTeam": "Salernitana",
  "AwayTeam": "Cagliari",
  "Result": "",
  "EventType": "schedule",
  "League": "S-A"
},
{
  "Match": "357",
  "Round": "36",
  "GameDate": "2022-05-08 23:00",
  "Location": "Mapei Stadium",
  "HomeTeam": "Sassuolo",
  "AwayTeam": "Udinese",
  "Result": "",
  "EventType": "schedule",
  "League": "S-A"
},
{
  "Match": "358",
  "Round": "36",
  "GameDate": "2022-05-08 23:00",
  "Location": "Alberto Picco",
  "HomeTeam": "Spezia",
  "AwayTeam": "Atalanta",
  "Result": "",
  "EventType": "schedule",
  "League": "S-A"
},
{
  "Match": "359",
  "Round": "36",
  "GameDate": "2022-05-08 23:00",
  "Location": "Olimpico Grande Torino",
  "HomeTeam": "Torino",
  "AwayTeam": "Napoli",
  "Result": "",
  "EventType": "schedule",
  "League": "S-A"
},
{
  "Match": "360",
  "Round": "36",
  "GameDate": "2022-05-08 23:00",
  "Location": "Pier Luigi Penzo",
  "HomeTeam": "Venezia",
  "AwayTeam": "Bologna",
  "Result": "",
  "EventType": "schedule",
  "League": "S-A"
},
{
  "Match": "361",
  "Round": "37",
  "GameDate": "2022-05-15 23:00",
  "Location": "Renato Dall'Ara",
  "HomeTeam": "Bologna",
  "AwayTeam": "Sassuolo",
  "Result": "",
  "EventType": "schedule",
  "League": "S-A"
},
{
  "Match": "362",
  "Round": "37",
  "GameDate": "2022-05-15 23:00",
  "Location": "Sardegna Arena",
  "HomeTeam": "Cagliari",
  "AwayTeam": "Inter",
  "Result": "",
  "EventType": "schedule",
  "League": "S-A"
},
{
  "Match": "363",
  "Round": "37",
  "GameDate": "2022-05-15 23:00",
  "Location": "Carlo Castellani",
  "HomeTeam": "Empoli",
  "AwayTeam": "Salernitana",
  "Result": "",
  "EventType": "schedule",
  "League": "S-A"
},
{
  "Match": "364",
  "Round": "37",
  "GameDate": "2022-05-15 23:00",
  "Location": "Marcantonio Bentegodi",
  "HomeTeam": "Hellas Verona",
  "AwayTeam": "Torino",
  "Result": "",
  "EventType": "schedule",
  "League": "S-A"
},
{
  "Match": "365",
  "Round": "37",
  "GameDate": "2022-05-15 23:00",
  "Location": "Allianz Stadium",
  "HomeTeam": "Juventus",
  "AwayTeam": "Lazio",
  "Result": "",
  "EventType": "schedule",
  "League": "S-A"
},
{
  "Match": "366",
  "Round": "37",
  "GameDate": "2022-05-15 23:00",
  "Location": "Giuseppe Meazza",
  "HomeTeam": "Milan",
  "AwayTeam": "Atalanta",
  "Result": "",
  "EventType": "schedule",
  "League": "S-A"
},
{
  "Match": "367",
  "Round": "37",
  "GameDate": "2022-05-15 23:00",
  "Location": "Diego Armando Maradona",
  "HomeTeam": "Napoli",
  "AwayTeam": "Genoa",
  "Result": "",
  "EventType": "schedule",
  "League": "S-A"
},
{
  "Match": "368",
  "Round": "37",
  "GameDate": "2022-05-15 23:00",
  "Location": "Olimpico",
  "HomeTeam": "Roma",
  "AwayTeam": "Venezia",
  "Result": "",
  "EventType": "schedule",
  "League": "S-A"
},
{
  "Match": "369",
  "Round": "37",
  "GameDate": "2022-05-15 23:00",
  "Location": "Luigi Ferraris",
  "HomeTeam": "Sampdoria",
  "AwayTeam": "Fiorentina",
  "Result": "",
  "EventType": "schedule",
  "League": "S-A"
},
{
  "Match": "370",
  "Round": "37",
  "GameDate": "2022-05-15 23:00",
  "Location": "Stadio Friuli",
  "HomeTeam": "Udinese",
  "AwayTeam": "Spezia",
  "Result": "",
  "EventType": "schedule",
  "League": "S-A"
},
{
  "Match": "371",
  "Round": "38",
  "GameDate": "2022-05-22 23:00",
  "Location": "Gewiss Stadium",
  "HomeTeam": "Atalanta",
  "AwayTeam": "Empoli",
  "Result": "",
  "EventType": "schedule",
  "League": "S-A"
},
{
  "Match": "372",
  "Round": "38",
  "GameDate": "2022-05-22 23:00",
  "Location": "Artemio Franchi",
  "HomeTeam": "Fiorentina",
  "AwayTeam": "Juventus",
  "Result": "",
  "EventType": "schedule",
  "League": "S-A"
},
{
  "Match": "373",
  "Round": "38",
  "GameDate": "2022-05-22 23:00",
  "Location": "Luigi Ferraris",
  "HomeTeam": "Genoa",
  "AwayTeam": "Bologna",
  "Result": "",
  "EventType": "schedule",
  "League": "S-A"
},
{
  "Match": "374",
  "Round": "38",
  "GameDate": "2022-05-22 23:00",
  "Location": "Giuseppe Meazza",
  "HomeTeam": "Inter",
  "AwayTeam": "Sampdoria",
  "Result": "",
  "EventType": "schedule",
  "League": "S-A"
},
{
  "Match": "375",
  "Round": "38",
  "GameDate": "2022-05-22 23:00",
  "Location": "Olimpico",
  "HomeTeam": "Lazio",
  "AwayTeam": "Hellas Verona",
  "Result": "",
  "EventType": "schedule",
  "League": "S-A"
},
{
  "Match": "376",
  "Round": "38",
  "GameDate": "2022-05-22 23:00",
  "Location": "Arechi",
  "HomeTeam": "Salernitana",
  "AwayTeam": "Udinese",
  "Result": "",
  "EventType": "schedule",
  "League": "S-A"
},
{
  "Match": "377",
  "Round": "38",
  "GameDate": "2022-05-22 23:00",
  "Location": "Mapei Stadium",
  "HomeTeam": "Sassuolo",
  "AwayTeam": "Milan",
  "Result": "",
  "EventType": "schedule",
  "League": "S-A"
},
{
  "Match": "378",
  "Round": "38",
  "GameDate": "2022-05-22 23:00",
  "Location": "Alberto Picco",
  "HomeTeam": "Spezia",
  "AwayTeam": "Napoli",
  "Result": "",
  "EventType": "schedule",
  "League": "S-A"
},
{
  "Match": "379",
  "Round": "38",
  "GameDate": "2022-05-22 23:00",
  "Location": "Olimpico Grande Torino",
  "HomeTeam": "Torino",
  "AwayTeam": "Roma",
  "Result": "",
  "EventType": "schedule",
  "League": "S-A"
},
{
  "Match": "380",
  "Round": "38",
  "GameDate": "2022-05-22 23:00",
  "Location": "Pier Luigi Penzo",
  "HomeTeam": "Venezia",
  "AwayTeam": "Cagliari",
  "Result": "",
  "EventType": "schedule",
  "League": "S-A"
},
]
